{
  "DeclareAcronym{}{}": {
    "command": "DeclareAcronym{id}{short = , long = }",
    "package": "acro",
    "snippet": "DeclareAcronym{${1:id}}{${2:short = , long = }}"
  },
  "ac{}": {
    "command": "ac{id}",
    "package": "acro",
    "snippet": "ac{${1:id}}"
  },
  "ac*{}": {
    "command": "ac*{id}",
    "package": "acro",
    "snippet": "ac*{${1:id}}"
  },
  "Ac{}": {
    "command": "Ac{id}",
    "package": "acro",
    "snippet": "Ac{${1:id}}"
  },
  "Ac*{}": {
    "command": "Ac*{id}",
    "package": "acro",
    "snippet": "Ac*{${1:id}}"
  },
  "acs{}": {
    "command": "acs{id}",
    "package": "acro",
    "snippet": "acs{${1:id}}"
  },
  "acs*{}": {
    "command": "acs*{id}",
    "package": "acro",
    "snippet": "acs*{${1:id}}"
  },
  "acl{}": {
    "command": "acl{id}",
    "package": "acro",
    "snippet": "acl{${1:id}}"
  },
  "acl*{}": {
    "command": "acl*{id}",
    "package": "acro",
    "snippet": "acl*{${1:id}}"
  },
  "Acl{}": {
    "command": "Acl{id}",
    "package": "acro",
    "snippet": "Acl{${1:id}}"
  },
  "Acl*{}": {
    "command": "Acl*{id}",
    "package": "acro",
    "snippet": "Acl*{${1:id}}"
  },
  "aca{}": {
    "command": "aca{id}",
    "package": "acro",
    "snippet": "aca{${1:id}}"
  },
  "aca*{}": {
    "command": "aca*{id}",
    "package": "acro",
    "snippet": "aca*{${1:id}}"
  },
  "acf{}": {
    "command": "acf{id}",
    "package": "acro",
    "snippet": "acf{${1:id}}"
  },
  "acf*{}": {
    "command": "acf*{id}",
    "package": "acro",
    "snippet": "acf*{${1:id}}"
  },
  "Acf{}": {
    "command": "Acf{id}",
    "package": "acro",
    "snippet": "Acf{${1:id}}"
  },
  "Acf*{}": {
    "command": "Acf*{id}",
    "package": "acro",
    "snippet": "Acf*{${1:id}}"
  },
  "acp{}": {
    "command": "acp{id}",
    "package": "acro",
    "snippet": "acp{${1:id}}"
  },
  "acp*{}": {
    "command": "acp*{id}",
    "package": "acro",
    "snippet": "acp*{${1:id}}"
  },
  "Acp{}": {
    "command": "Acp{id}",
    "package": "acro",
    "snippet": "Acp{${1:id}}"
  },
  "Acp*{}": {
    "command": "Acp*{id}",
    "package": "acro",
    "snippet": "Acp*{${1:id}}"
  },
  "acsp{}": {
    "command": "acsp{id}",
    "package": "acro",
    "snippet": "acsp{${1:id}}"
  },
  "acsp*{}": {
    "command": "acsp*{id}",
    "package": "acro",
    "snippet": "acsp*{${1:id}}"
  },
  "aclp{}": {
    "command": "aclp{id}",
    "package": "acro",
    "snippet": "aclp{${1:id}}"
  },
  "aclp*{}": {
    "command": "aclp*{id}",
    "package": "acro",
    "snippet": "aclp*{${1:id}}"
  },
  "Aclp{}": {
    "command": "Aclp{id}",
    "package": "acro",
    "snippet": "Aclp{${1:id}}"
  },
  "Aclp*{}": {
    "command": "Aclp*{id}",
    "package": "acro",
    "snippet": "Aclp*{${1:id}}"
  },
  "acap{}": {
    "command": "acap{id}",
    "package": "acro",
    "snippet": "acap{${1:id}}"
  },
  "acap*{}": {
    "command": "acap*{id}",
    "package": "acro",
    "snippet": "acap*{${1:id}}"
  },
  "acfp{}": {
    "command": "acfp{id}",
    "package": "acro",
    "snippet": "acfp{${1:id}}"
  },
  "acfp*{}": {
    "command": "acfp*{id}",
    "package": "acro",
    "snippet": "acfp*{${1:id}}"
  },
  "Acfp{}": {
    "command": "Acfp{id}",
    "package": "acro",
    "snippet": "Acfp{${1:id}}"
  },
  "Acfp*{}": {
    "command": "Acfp*{id}",
    "package": "acro",
    "snippet": "Acfp*{${1:id}}"
  },
  "acfirstupper{}": {
    "command": "acfirstupper{token list}",
    "package": "acro",
    "snippet": "acfirstupper{${1:token list}}"
  },
  "acflike{}{}": {
    "command": "acflike{id}{instead of long form}",
    "package": "acro",
    "snippet": "acflike{${1:id}}{${2:instead of long form}}"
  },
  "acflike*{}{}": {
    "command": "acflike*{id}{instead of long form}",
    "package": "acro",
    "snippet": "acflike*{${1:id}}{${2:instead of long form}}"
  },
  "acfplike{}{}": {
    "command": "acfplike{id}{instead of long form}",
    "package": "acro",
    "snippet": "acfplike{${1:id}}{${2:instead of long form}}"
  },
  "acfplike*{}{}": {
    "command": "acfplike*{id}{instead of long form}",
    "package": "acro",
    "snippet": "acfplike*{${1:id}}{${2:instead of long form}}"
  },
  "acreset{}": {
    "command": "acreset{comma separated list of id}",
    "package": "acro",
    "snippet": "acreset{${1:comma separated list of id}}"
  },
  "acresetall": {
    "command": "acresetall",
    "package": "acro",
    "snippet": "acresetall"
  },
  "acifused{}{}{}": {
    "command": "acifused{id}{true}{false}",
    "package": "acro",
    "snippet": "acifused{${1:id}}{${2:true}}{${3:false}}"
  },
  "acuse{}": {
    "command": "acuse{comma separated list of ids}",
    "package": "acro",
    "snippet": "acuse{${1:comma separated list of ids}}"
  },
  "acuseall": {
    "command": "acuseall",
    "package": "acro",
    "snippet": "acuseall"
  },
  "printacronyms[]": {
    "command": "printacronyms[options]",
    "package": "acro",
    "snippet": "printacronyms[${1:options}]"
  },
  "acsetup{}": {
    "command": "acsetup{options}",
    "package": "acro",
    "snippet": "acsetup{${1:options}}"
  }
}