{
  "includes": [
    "iftex",
    "keyval",
    "color",
    "infwaerr",
    "ltxcmds",
    "kvoptions",
    "pdftexcmds",
    "pdfescape",
    "hyperref",
    "hycolor"
  ],
  "cmds": {
    "attachfile{}": {
      "command": "attachfile{}",
      "snippet": "attachfile{${1:file}}",
      "option": "",
      "keyvals": [],
      "keyvalindex": -1
    },
    "attachfile[]{}": {
      "command": "attachfile[]{}",
      "snippet": "attachfile[${2:options}]{${1:file}}",
      "option": "",
      "keyvals": [],
      "keyvalindex": -1
    },
    "noattachfile": {
      "command": "noattachfile",
      "snippet": "noattachfile",
      "option": "",
      "keyvals": [],
      "keyvalindex": -1
    },
    "noattachfile[]": {
      "command": "noattachfile[]",
      "snippet": "noattachfile[${1:options}]",
      "option": "",
      "keyvals": [],
      "keyvalindex": -1
    },
    "notextattachfile{}": {
      "command": "notextattachfile{}",
      "snippet": "notextattachfile{${1:text}}",
      "option": "",
      "keyvals": [],
      "keyvalindex": -1
    },
    "notextattachfile[]{}": {
      "command": "notextattachfile[]{}",
      "snippet": "notextattachfile[${2:options}]{${1:text}}",
      "option": "",
      "keyvals": [],
      "keyvalindex": -1
    },
    "textattachfile{}{}": {
      "command": "textattachfile{}{}",
      "snippet": "textattachfile{${1:file}}{${2:text}}",
      "option": "",
      "keyvals": [],
      "keyvalindex": -1
    },
    "textattachfile[]{}{}": {
      "command": "textattachfile[]{}{}",
      "snippet": "textattachfile[${3:options}]{${1:file}}{${2:text}}",
      "option": "",
      "keyvals": [],
      "keyvalindex": -1
    },
    "attachfilesetup{}": {
      "command": "attachfilesetup{}",
      "snippet": "attachfilesetup{${1:options}}",
      "option": "",
      "keyvals": [],
      "keyvalindex": -1
    }
  },
  "envs": {},
  "options": [
    "appearance",
    "author=",
    "color=",
    "created=",
    "date=",
    "description=",
    "icon=",
    "mimetype=",
    "modified=",
    "print",
    "size=",
    "subject=",
    "timezone=",
    "zoom",
    "scale=",
    "ucfilespec=",
    "annotname=",
    "draft",
    "final",
    "nofiles",
    "pdftex",
    "luatex",
    "dvips",
    "dvipdfmx",
    "xetex",
    "driverfallback="
  ]
}