{
  "includes": [
    "xkeyval",
    "etoolbox",
    "fancyhdr",
    "fancybox",
    "ifthen",
    "lastpage",
    "listings",
    "appendix",
    "paralist",
    "amsthm",
    "amsfonts",
    "amsmath",
    "bm",
    "amssymb",
    "mathrsfs",
    "latexsym",
    "longtable",
    "multirow",
    "hhline",
    "tabularx",
    "array",
    "flafter",
    "pifont",
    "calc",
    "colortbl",
    "booktabs",
    "geometry",
    "fontenc",
    "berasans",
    "hyperref",
    "ifpdf",
    "ifxetex",
    "environ",
    "graphicx",
    "epstopdf",
    "xcolor"
  ],
  "cmds": {
    "mcmsetup{}": {
      "command": "mcmsetup{}",
      "snippet": "mcmsetup{${1:options}}",
      "option": "",
      "keyvals": [
        "CTeX",
        "titlepage",
        "abstract",
        "sheet",
        "titleinsheet",
        "keywordsinsheet",
        "tcn=",
        "problem="
      ],
      "keyvalindex": 0
    },
    "dif": {
      "command": "dif",
      "snippet": "dif",
      "option": "",
      "keyvals": [],
      "keyvalindex": -1
    },
    "headset": {
      "command": "headset",
      "snippet": "headset",
      "option": "",
      "keyvals": [],
      "keyvalindex": -1
    },
    "keywordsname": {
      "command": "keywordsname",
      "snippet": "keywordsname",
      "option": "",
      "keyvals": [],
      "keyvalindex": -1
    },
    "lhaddress{}": {
      "command": "lhaddress{}",
      "snippet": "lhaddress{${1:address%text}}",
      "option": "",
      "keyvals": [],
      "keyvalindex": -1
    },
    "lstbasicfont": {
      "command": "lstbasicfont",
      "snippet": "lstbasicfont",
      "option": "",
      "keyvals": [],
      "keyvalindex": -1
    },
    "makesheet": {
      "command": "makesheet",
      "snippet": "makesheet",
      "option": "",
      "keyvals": [],
      "keyvalindex": -1
    },
    "MCMversion": {
      "command": "MCMversion",
      "snippet": "MCMversion",
      "option": "",
      "keyvals": [],
      "keyvalindex": -1
    },
    "me": {
      "command": "me",
      "snippet": "me",
      "option": "",
      "keyvals": [],
      "keyvalindex": -1
    },
    "memodate{}": {
      "command": "memodate{}",
      "snippet": "memodate{${1:date}}",
      "option": "",
      "keyvals": [],
      "keyvalindex": -1
    },
    "memofrom{}": {
      "command": "memofrom{}",
      "snippet": "memofrom{${1:name}}",
      "option": "",
      "keyvals": [],
      "keyvalindex": -1
    },
    "memologo{}": {
      "command": "memologo{}",
      "snippet": "memologo{${1:logo code}}",
      "option": "",
      "keyvals": [],
      "keyvalindex": -1
    },
    "memosubject{}": {
      "command": "memosubject{}",
      "snippet": "memosubject{${1:subject%text}}",
      "option": "",
      "keyvals": [],
      "keyvalindex": -1
    },
    "memoto{}": {
      "command": "memoto{}",
      "snippet": "memoto{${1:name}}",
      "option": "",
      "keyvals": [],
      "keyvalindex": -1
    },
    "mi": {
      "command": "mi",
      "snippet": "mi",
      "option": "",
      "keyvals": [],
      "keyvalindex": -1
    },
    "team": {
      "command": "team",
      "snippet": "team",
      "option": "",
      "keyvals": [],
      "keyvalindex": -1
    },
    "problem{}": {
      "command": "problem{}",
      "snippet": "problem{${1:question}}",
      "option": "",
      "keyvals": [],
      "keyvalindex": -1
    },
    "DH": {
      "command": "DH",
      "snippet": "DH",
      "option": "",
      "keyvals": [],
      "keyvalindex": -1
    },
    "dh": {
      "command": "dh",
      "snippet": "dh",
      "option": "",
      "keyvals": [],
      "keyvalindex": -1
    },
    "dj": {
      "command": "dj",
      "snippet": "dj",
      "option": "",
      "keyvals": [],
      "keyvalindex": -1
    },
    "DJ": {
      "command": "DJ",
      "snippet": "DJ",
      "option": "",
      "keyvals": [],
      "keyvalindex": -1
    },
    "guillemetleft": {
      "command": "guillemetleft",
      "snippet": "guillemetleft",
      "option": "",
      "keyvals": [],
      "keyvalindex": -1
    },
    "guillemetright": {
      "command": "guillemetright",
      "snippet": "guillemetright",
      "option": "",
      "keyvals": [],
      "keyvalindex": -1
    },
    "guillemotleft": {
      "command": "guillemotleft",
      "snippet": "guillemotleft",
      "option": "",
      "keyvals": [],
      "keyvalindex": -1
    },
    "guillemotright": {
      "command": "guillemotright",
      "snippet": "guillemotright",
      "option": "",
      "keyvals": [],
      "keyvalindex": -1
    },
    "guilsinglleft": {
      "command": "guilsinglleft",
      "snippet": "guilsinglleft",
      "option": "",
      "keyvals": [],
      "keyvalindex": -1
    },
    "guilsinglright": {
      "command": "guilsinglright",
      "snippet": "guilsinglright",
      "option": "",
      "keyvals": [],
      "keyvalindex": -1
    },
    "Hwithstroke": {
      "command": "Hwithstroke",
      "snippet": "Hwithstroke",
      "option": "",
      "keyvals": [],
      "keyvalindex": -1
    },
    "hwithstroke": {
      "command": "hwithstroke",
      "snippet": "hwithstroke",
      "option": "",
      "keyvals": [],
      "keyvalindex": -1
    },
    "k{}": {
      "command": "k{}",
      "snippet": "k{${1:arg}}",
      "option": "",
      "keyvals": [],
      "keyvalindex": -1
    },
    "NG": {
      "command": "NG",
      "snippet": "NG",
      "option": "",
      "keyvals": [],
      "keyvalindex": -1
    },
    "ng": {
      "command": "ng",
      "snippet": "ng",
      "option": "",
      "keyvals": [],
      "keyvalindex": -1
    },
    "quotedblbase": {
      "command": "quotedblbase",
      "snippet": "quotedblbase",
      "option": "",
      "keyvals": [],
      "keyvalindex": -1
    },
    "quotesinglbase": {
      "command": "quotesinglbase",
      "snippet": "quotesinglbase",
      "option": "",
      "keyvals": [],
      "keyvalindex": -1
    },
    "textogonekcentered{}": {
      "command": "textogonekcentered{}",
      "snippet": "textogonekcentered{${1:arg}}",
      "option": "",
      "keyvals": [],
      "keyvalindex": -1
    },
    "textquotedbl": {
      "command": "textquotedbl",
      "snippet": "textquotedbl",
      "option": "",
      "keyvals": [],
      "keyvalindex": -1
    },
    "th": {
      "command": "th",
      "snippet": "th",
      "option": "",
      "keyvals": [],
      "keyvalindex": -1
    },
    "TH": {
      "command": "TH",
      "snippet": "TH",
      "option": "",
      "keyvals": [],
      "keyvalindex": -1
    }
  },
  "envs": {
    "Corollary": {
      "name": "Corollary",
      "detail": "Corollary",
      "snippet": "",
      "option": "",
      "keyvals": [],
      "keyvalindex": -1
    },
    "Corollary[]": {
      "name": "Corollary",
      "detail": "Corollary[]",
      "snippet": "[${1:heading%text}]",
      "option": "",
      "keyvals": [],
      "keyvalindex": -1
    },
    "Definition": {
      "name": "Definition",
      "detail": "Definition",
      "snippet": "",
      "option": "",
      "keyvals": [],
      "keyvalindex": -1
    },
    "Definition[]": {
      "name": "Definition",
      "detail": "Definition[]",
      "snippet": "[${1:heading%text}]",
      "option": "",
      "keyvals": [],
      "keyvalindex": -1
    },
    "Example": {
      "name": "Example",
      "detail": "Example",
      "snippet": "",
      "option": "",
      "keyvals": [],
      "keyvalindex": -1
    },
    "Example[]": {
      "name": "Example",
      "detail": "Example[]",
      "snippet": "[${1:heading%text}]",
      "option": "",
      "keyvals": [],
      "keyvalindex": -1
    },
    "Lemma": {
      "name": "Lemma",
      "detail": "Lemma",
      "snippet": "",
      "option": "",
      "keyvals": [],
      "keyvalindex": -1
    },
    "Lemma[]": {
      "name": "Lemma",
      "detail": "Lemma[]",
      "snippet": "[${1:heading%text}]",
      "option": "",
      "keyvals": [],
      "keyvalindex": -1
    },
    "letter{}": {
      "name": "letter",
      "detail": "letter{}",
      "snippet": "{${1:salutation%text}}",
      "option": "",
      "keyvals": [],
      "keyvalindex": -1
    },
    "keywords": {
      "name": "keywords",
      "detail": "keywords",
      "snippet": "",
      "option": "",
      "keyvals": [],
      "keyvalindex": -1
    },
    "memo": {
      "name": "memo",
      "detail": "memo",
      "snippet": "",
      "option": "",
      "keyvals": [],
      "keyvalindex": -1
    },
    "memo[]": {
      "name": "memo",
      "detail": "memo[]",
      "snippet": "[${1:title%text}]",
      "option": "",
      "keyvals": [],
      "keyvalindex": -1
    },
    "Proposition": {
      "name": "Proposition",
      "detail": "Proposition",
      "snippet": "",
      "option": "",
      "keyvals": [],
      "keyvalindex": -1
    },
    "Proposition[]": {
      "name": "Proposition",
      "detail": "Proposition[]",
      "snippet": "[${1:heading%text}]",
      "option": "",
      "keyvals": [],
      "keyvalindex": -1
    },
    "Theorem": {
      "name": "Theorem",
      "detail": "Theorem",
      "snippet": "",
      "option": "",
      "keyvals": [],
      "keyvalindex": -1
    },
    "Theorem[]": {
      "name": "Theorem",
      "detail": "Theorem[]",
      "snippet": "[${1:heading%text}]",
      "option": "",
      "keyvals": [],
      "keyvalindex": -1
    }
  },
  "options": []
}