{
  "includes": [
    "xspace"
  ],
  "cmds": {
    "ece": {
      "command": "ece",
      "snippet": "ece",
      "option": "",
      "keyvals": [],
      "keyvalindex": -1
    },
    "que": {
      "command": "que",
      "snippet": "que",
      "option": "",
      "keyvals": [],
      "keyvalindex": -1
    },
    "eqe": {
      "command": "eqe",
      "snippet": "eqe",
      "option": "",
      "keyvals": [],
      "keyvalindex": -1
    },
    "qee": {
      "command": "qee",
      "snippet": "qee",
      "option": "",
      "keyvals": [],
      "keyvalindex": -1
    },
    "ele": {
      "command": "ele",
      "snippet": "ele",
      "option": "",
      "keyvals": [],
      "keyvalindex": -1
    },
    "elq": {
      "command": "elq",
      "snippet": "elq",
      "option": "",
      "keyvals": [],
      "keyvalindex": -1
    },
    "eco": {
      "command": "eco",
      "snippet": "eco",
      "option": "",
      "keyvals": [],
      "keyvalindex": -1
    },
    "coe": {
      "command": "coe",
      "snippet": "coe",
      "option": "",
      "keyvals": [],
      "keyvalindex": -1
    },
    "beb": {
      "command": "beb",
      "snippet": "beb",
      "option": "",
      "keyvals": [],
      "keyvalindex": -1
    },
    "vev": {
      "command": "vev",
      "snippet": "vev",
      "option": "",
      "keyvals": [],
      "keyvalindex": -1
    }
  },
  "envs": {},
  "options": []
}