{
  "includes": [],
  "cmds": {
    "Graypersecondnp": {
      "command": "Graypersecondnp",
      "snippet": "Graypersecondnp",
      "option": "",
      "keyvals": []
    },
    "metrepersquaresecondnp": {
      "command": "metrepersquaresecondnp",
      "snippet": "metrepersquaresecondnp",
      "option": "",
      "keyvals": []
    },
    "joulepermolenp": {
      "command": "joulepermolenp",
      "snippet": "joulepermolenp",
      "option": "",
      "keyvals": []
    },
    "molepercubicmetrenp": {
      "command": "molepercubicmetrenp",
      "snippet": "molepercubicmetrenp",
      "option": "",
      "keyvals": []
    },
    "radianpersquaresecondnp": {
      "command": "radianpersquaresecondnp",
      "snippet": "radianpersquaresecondnp",
      "option": "",
      "keyvals": []
    },
    "kilogramsquaremetrepersecondnp": {
      "command": "kilogramsquaremetrepersecondnp",
      "snippet": "kilogramsquaremetrepersecondnp",
      "option": "",
      "keyvals": []
    },
    "radianpersecondnp": {
      "command": "radianpersecondnp",
      "snippet": "radianpersecondnp",
      "option": "",
      "keyvals": []
    },
    "Squaremetrepercubicmetrenp": {
      "command": "Squaremetrepercubicmetrenp",
      "snippet": "Squaremetrepercubicmetrenp",
      "option": "",
      "keyvals": []
    },
    "coulombpermolnp": {
      "command": "coulombpermolnp",
      "snippet": "coulombpermolnp",
      "option": "",
      "keyvals": []
    },
    "amperepersquaremetrenp": {
      "command": "amperepersquaremetrenp",
      "snippet": "amperepersquaremetrenp",
      "option": "",
      "keyvals": []
    },
    "kilogrampercubicmetrenp": {
      "command": "kilogrampercubicmetrenp",
      "snippet": "kilogrampercubicmetrenp",
      "option": "",
      "keyvals": []
    },
    "Squaremetrepernewtonsecondnp": {
      "command": "Squaremetrepernewtonsecondnp",
      "snippet": "Squaremetrepernewtonsecondnp",
      "option": "",
      "keyvals": []
    },
    "pascalsecondnp": {
      "command": "pascalsecondnp",
      "snippet": "pascalsecondnp",
      "option": "",
      "keyvals": []
    },
    "coulombpercubicmetrenp": {
      "command": "coulombpercubicmetrenp",
      "snippet": "coulombpercubicmetrenp",
      "option": "",
      "keyvals": []
    },
    "voltpermetrenp": {
      "command": "voltpermetrenp",
      "snippet": "voltpermetrenp",
      "option": "",
      "keyvals": []
    },
    "coulombpersquaremetrenp": {
      "command": "coulombpersquaremetrenp",
      "snippet": "coulombpersquaremetrenp",
      "option": "",
      "keyvals": []
    },
    "faradpermetrenp": {
      "command": "faradpermetrenp",
      "snippet": "faradpermetrenp",
      "option": "",
      "keyvals": []
    },
    "wattpersquaremetrenp": {
      "command": "wattpersquaremetrenp",
      "snippet": "wattpersquaremetrenp",
      "option": "",
      "keyvals": []
    },
    "joulepersquaremetrenp": {
      "command": "joulepersquaremetrenp",
      "snippet": "joulepersquaremetrenp",
      "option": "",
      "keyvals": []
    },
    "newtonpercubicmetrenp": {
      "command": "newtonpercubicmetrenp",
      "snippet": "newtonpercubicmetrenp",
      "option": "",
      "keyvals": []
    },
    "newtonperkilogramnp": {
      "command": "newtonperkilogramnp",
      "snippet": "newtonperkilogramnp",
      "option": "",
      "keyvals": []
    },
    "jouleperkelvinnp": {
      "command": "jouleperkelvinnp",
      "snippet": "jouleperkelvinnp",
      "option": "",
      "keyvals": []
    },
    "jouleperkilogramnp": {
      "command": "jouleperkilogramnp",
      "snippet": "jouleperkilogramnp",
      "option": "",
      "keyvals": []
    },
    "coulombperkilogramnp": {
      "command": "coulombperkilogramnp",
      "snippet": "coulombperkilogramnp",
      "option": "",
      "keyvals": []
    },
    "Squaremetrepersecondnp": {
      "command": "Squaremetrepersecondnp",
      "snippet": "Squaremetrepersecondnp",
      "option": "",
      "keyvals": []
    },
    "Squaremetrepersquaresecondnp": {
      "command": "Squaremetrepersquaresecondnp",
      "snippet": "Squaremetrepersquaresecondnp",
      "option": "",
      "keyvals": []
    },
    "kilogrammetrepersecondnp": {
      "command": "kilogrammetrepersecondnp",
      "snippet": "kilogrammetrepersecondnp",
      "option": "",
      "keyvals": []
    },
    "candelapersquaremetrenp": {
      "command": "candelapersquaremetrenp",
      "snippet": "candelapersquaremetrenp",
      "option": "",
      "keyvals": []
    },
    "amperepermetrenp": {
      "command": "amperepermetrenp",
      "snippet": "amperepermetrenp",
      "option": "",
      "keyvals": []
    },
    "jouleperteslanp": {
      "command": "jouleperteslanp",
      "snippet": "jouleperteslanp",
      "option": "",
      "keyvals": []
    },
    "henrypermetrenp": {
      "command": "henrypermetrenp",
      "snippet": "henrypermetrenp",
      "option": "",
      "keyvals": []
    },
    "kilogrampersecondnp": {
      "command": "kilogrampersecondnp",
      "snippet": "kilogrampersecondnp",
      "option": "",
      "keyvals": []
    },
    "kilogrampersquaremetresecondnp": {
      "command": "kilogrampersquaremetresecondnp",
      "snippet": "kilogrampersquaremetresecondnp",
      "option": "",
      "keyvals": []
    },
    "kilogrampersquaremetrenp": {
      "command": "kilogrampersquaremetrenp",
      "snippet": "kilogrampersquaremetrenp",
      "option": "",
      "keyvals": []
    },
    "kilogrampermetrenp": {
      "command": "kilogrampermetrenp",
      "snippet": "kilogrampermetrenp",
      "option": "",
      "keyvals": []
    },
    "joulepermolekelvinnp": {
      "command": "joulepermolekelvinnp",
      "snippet": "joulepermolekelvinnp",
      "option": "",
      "keyvals": []
    },
    "kilogramperkilomolenp": {
      "command": "kilogramperkilomolenp",
      "snippet": "kilogramperkilomolenp",
      "option": "",
      "keyvals": []
    },
    "kilogramsquaremetrenp": {
      "command": "kilogramsquaremetrenp",
      "snippet": "kilogramsquaremetrenp",
      "option": "",
      "keyvals": []
    },
    "kilogrammetrepersquaresecondnp": {
      "command": "kilogrammetrepersquaresecondnp",
      "snippet": "kilogrammetrepersquaresecondnp",
      "option": "",
      "keyvals": []
    },
    "newtonpersquaremetrenp": {
      "command": "newtonpersquaremetrenp",
      "snippet": "newtonpersquaremetrenp",
      "option": "",
      "keyvals": []
    },
    "persquaremetresecondnp": {
      "command": "persquaremetresecondnp",
      "snippet": "persquaremetresecondnp",
      "option": "",
      "keyvals": []
    },
    "wattperkilogramnp": {
      "command": "wattperkilogramnp",
      "snippet": "wattperkilogramnp",
      "option": "",
      "keyvals": []
    },
    "wattpercubicmetrenp": {
      "command": "wattpercubicmetrenp",
      "snippet": "wattpercubicmetrenp",
      "option": "",
      "keyvals": []
    },
    "wattpersquaremetresteradiannp": {
      "command": "wattpersquaremetresteradiannp",
      "snippet": "wattpersquaremetresteradiannp",
      "option": "",
      "keyvals": []
    },
    "jouleperkilogramkelvinnp": {
      "command": "jouleperkilogramkelvinnp",
      "snippet": "jouleperkilogramkelvinnp",
      "option": "",
      "keyvals": []
    },
    "Squaremetreperkilogramnp": {
      "command": "Squaremetreperkilogramnp",
      "snippet": "Squaremetreperkilogramnp",
      "option": "",
      "keyvals": []
    },
    "cubicmetreperkilogramnp": {
      "command": "cubicmetreperkilogramnp",
      "snippet": "cubicmetreperkilogramnp",
      "option": "",
      "keyvals": []
    },
    "newtonpermetrenp": {
      "command": "newtonpermetrenp",
      "snippet": "newtonpermetrenp",
      "option": "",
      "keyvals": []
    },
    "wattpermetrekelvinnp": {
      "command": "wattpermetrekelvinnp",
      "snippet": "wattpermetrekelvinnp",
      "option": "",
      "keyvals": []
    },
    "newtonmetrenp": {
      "command": "newtonmetrenp",
      "snippet": "newtonmetrenp",
      "option": "",
      "keyvals": []
    },
    "Squaremetrepercubicsecondnp": {
      "command": "Squaremetrepercubicsecondnp",
      "snippet": "Squaremetrepercubicsecondnp",
      "option": "",
      "keyvals": []
    },
    "metrepersecondnp": {
      "command": "metrepersecondnp",
      "snippet": "metrepersecondnp",
      "option": "",
      "keyvals": []
    },
    "joulepercubicmetrenp": {
      "command": "joulepercubicmetrenp",
      "snippet": "joulepercubicmetrenp",
      "option": "",
      "keyvals": []
    },
    "kilogrampercubicmetrecoulombnp": {
      "command": "kilogrampercubicmetrecoulombnp",
      "snippet": "kilogrampercubicmetrecoulombnp",
      "option": "",
      "keyvals": []
    },
    "cubicmetrepersecondnp": {
      "command": "cubicmetrepersecondnp",
      "snippet": "cubicmetrepersecondnp",
      "option": "",
      "keyvals": []
    },
    "kilogrampersecondcubicmetrenp": {
      "command": "kilogrampersecondcubicmetrenp",
      "snippet": "kilogrampersecondcubicmetrenp",
      "option": "",
      "keyvals": []
    }
  },
  "envs": {},
  "options": []
}