{
  "includes": [
    "ifthen",
    "textcomp",
    "xcolor",
    "listingsutf8",
    "inputenc"
  ],
  "cmds": {},
  "envs": {
    "CCode": {
      "name": "CCode",
      "detail": "CCode",
      "snippet": "",
      "option": "",
      "keyvals": [],
      "keyvalindex": -1
    },
    "CCode[]": {
      "name": "CCode",
      "detail": "CCode[]",
      "snippet": "[${1:options}]",
      "option": "",
      "keyvals": [
        "inputpath=",
        "aboveskip=",
        "belowskip=",
        "lineskip=",
        "boxpos=",
        "print",
        "showlines",
        "emptylines=",
        "emptylines=*",
        "gobble=",
        "style=",
        "language=",
        "language=[",
        "alsolanguage=",
        "alsolanguage=[",
        "defaultdialect=[",
        "printpod",
        "usekeywordsintag",
        "tagstyle=",
        "markfirstintag=",
        "makemacrouse",
        "basicstyle=",
        "identifierstyle=",
        "commentstyle=",
        "stringstyle=",
        "keywordstyle=",
        "keywordstyle=[",
        "keywordstyle=[",
        "ndkeywordstyle=",
        "classoffset=",
        "texcsstyle=",
        "texcsstyle=[",
        "texcsstyle=*[",
        "directivestyle=",
        "emph={",
        "emph=[",
        "moreemph={",
        "moreemph=[",
        "deleteemph={",
        "deleteemph=[",
        "emphstyle={",
        "emphstyle=[",
        "delim=[",
        "delim=*[",
        "delim=**[",
        "moredelim=[",
        "moredelim=*[",
        "moredelim=**[",
        "deletedelim=[",
        "deletedelim=*[",
        "deletedelim=**[",
        "extendedchars",
        "inputencoding=",
        "upquote",
        "tabsize=",
        "showtabs",
        "tab=",
        "showspaces",
        "showstringspaces",
        "formfeed=",
        "numbers=",
        "stepnumber=",
        "numberfirstline",
        "numberstyle=",
        "numbersep=",
        "numberblanklines",
        "firstnumber=",
        "name=",
        "title=",
        "caption={",
        "caption={[",
        "label=",
        "nolol",
        "numberbychapter",
        "captionpos=",
        "abovecaptionskip=",
        "belowcaptionskip=",
        "linewidth=",
        "xleftmargin=",
        "xrightmargin=",
        "resetmargins",
        "breaklines",
        "breakatwhitespace",
        "prebreak=",
        "postbreak=",
        "breakindent=",
        "breakautoindent",
        "frame=",
        "frameround=",
        "framesep=",
        "rulesep=",
        "framerule=",
        "framexleftmargin=",
        "framexrightmargin=",
        "framextopmargin=",
        "framexbottommargin=",
        "backgroundcolor=",
        "rulecolor=",
        "fillcolor=",
        "rulesepcolor=",
        "frameshape={",
        "index={",
        "index=[",
        "index=[",
        "moreindex={",
        "moreindex=[",
        "moreindex=[",
        "deleteindex={",
        "deleteindex=[",
        "deleteindex=[",
        "indexstyle=",
        "indexstyle=[",
        "columns=",
        "columns=[",
        "flexiblecolumns",
        "keepspaces",
        "basewidth=",
        "fontadjust",
        "texcl",
        "mathescape",
        "escapechar=",
        "escapeinside=",
        "escapebegin=",
        "escapeend=",
        "fancyvrb",
        "fvcmdparams=",
        "morefvcmdparams=",
        "literate={",
        "literate=*{",
        "rangebeginprefix=",
        "rangebeginsuffix=",
        "rangeendprefix=",
        "rangeendsuffix=",
        "rangeprefix=",
        "rangesuffix=",
        "includerangemarker",
        "multicols=",
        "float",
        "float=",
        "float=*",
        "floatplacement=",
        "firstline=",
        "lastline=",
        "linerange={",
        "consecutivenumbers",
        "keywordsprefix=",
        "keywords={",
        "keywords=[",
        "morekeywords={",
        "morekeywords=[",
        "deletekeywords={",
        "deletekeywords=[",
        "ndkeywords={",
        "moreendkeywords={",
        "deleteendkeywords={",
        "texcs={",
        "texcs=[",
        "moretexcs={",
        "moretexcs=[",
        "deletetexcs={",
        "deletetexcs=[",
        "directives={",
        "moredirectives={",
        "deletedirectives={",
        "sensitive",
        "alsoletter={",
        "alsodigit={",
        "alsoother={",
        "otherkeywords={",
        "tag=",
        "string=",
        "string=[",
        "morestring=",
        "morestring=[",
        "deletestring=",
        "deletestring=[",
        "comment=",
        "comment=[",
        "morecomment=",
        "morecomment=[",
        "deletecomment=",
        "deletecomment=[",
        "keywordcomment={",
        "morekeywordcomment={",
        "deletekeywordcomment={",
        "keywordcommentsemicolon={",
        "podcomment"
      ],
      "keyvalindex": 0
    },
    "CppCode": {
      "name": "CppCode",
      "detail": "CppCode",
      "snippet": "",
      "option": "",
      "keyvals": [],
      "keyvalindex": -1
    },
    "CppCode[]": {
      "name": "CppCode",
      "detail": "CppCode[]",
      "snippet": "[${1:options}]",
      "option": "",
      "keyvals": [
        "inputpath=",
        "aboveskip=",
        "belowskip=",
        "lineskip=",
        "boxpos=",
        "print",
        "showlines",
        "emptylines=",
        "emptylines=*",
        "gobble=",
        "style=",
        "language=",
        "language=[",
        "alsolanguage=",
        "alsolanguage=[",
        "defaultdialect=[",
        "printpod",
        "usekeywordsintag",
        "tagstyle=",
        "markfirstintag=",
        "makemacrouse",
        "basicstyle=",
        "identifierstyle=",
        "commentstyle=",
        "stringstyle=",
        "keywordstyle=",
        "keywordstyle=[",
        "keywordstyle=[",
        "ndkeywordstyle=",
        "classoffset=",
        "texcsstyle=",
        "texcsstyle=[",
        "texcsstyle=*[",
        "directivestyle=",
        "emph={",
        "emph=[",
        "moreemph={",
        "moreemph=[",
        "deleteemph={",
        "deleteemph=[",
        "emphstyle={",
        "emphstyle=[",
        "delim=[",
        "delim=*[",
        "delim=**[",
        "moredelim=[",
        "moredelim=*[",
        "moredelim=**[",
        "deletedelim=[",
        "deletedelim=*[",
        "deletedelim=**[",
        "extendedchars",
        "inputencoding=",
        "upquote",
        "tabsize=",
        "showtabs",
        "tab=",
        "showspaces",
        "showstringspaces",
        "formfeed=",
        "numbers=",
        "stepnumber=",
        "numberfirstline",
        "numberstyle=",
        "numbersep=",
        "numberblanklines",
        "firstnumber=",
        "name=",
        "title=",
        "caption={",
        "caption={[",
        "label=",
        "nolol",
        "numberbychapter",
        "captionpos=",
        "abovecaptionskip=",
        "belowcaptionskip=",
        "linewidth=",
        "xleftmargin=",
        "xrightmargin=",
        "resetmargins",
        "breaklines",
        "breakatwhitespace",
        "prebreak=",
        "postbreak=",
        "breakindent=",
        "breakautoindent",
        "frame=",
        "frameround=",
        "framesep=",
        "rulesep=",
        "framerule=",
        "framexleftmargin=",
        "framexrightmargin=",
        "framextopmargin=",
        "framexbottommargin=",
        "backgroundcolor=",
        "rulecolor=",
        "fillcolor=",
        "rulesepcolor=",
        "frameshape={",
        "index={",
        "index=[",
        "index=[",
        "moreindex={",
        "moreindex=[",
        "moreindex=[",
        "deleteindex={",
        "deleteindex=[",
        "deleteindex=[",
        "indexstyle=",
        "indexstyle=[",
        "columns=",
        "columns=[",
        "flexiblecolumns",
        "keepspaces",
        "basewidth=",
        "fontadjust",
        "texcl",
        "mathescape",
        "escapechar=",
        "escapeinside=",
        "escapebegin=",
        "escapeend=",
        "fancyvrb",
        "fvcmdparams=",
        "morefvcmdparams=",
        "literate={",
        "literate=*{",
        "rangebeginprefix=",
        "rangebeginsuffix=",
        "rangeendprefix=",
        "rangeendsuffix=",
        "rangeprefix=",
        "rangesuffix=",
        "includerangemarker",
        "multicols=",
        "float",
        "float=",
        "float=*",
        "floatplacement=",
        "firstline=",
        "lastline=",
        "linerange={",
        "consecutivenumbers",
        "keywordsprefix=",
        "keywords={",
        "keywords=[",
        "morekeywords={",
        "morekeywords=[",
        "deletekeywords={",
        "deletekeywords=[",
        "ndkeywords={",
        "moreendkeywords={",
        "deleteendkeywords={",
        "texcs={",
        "texcs=[",
        "moretexcs={",
        "moretexcs=[",
        "deletetexcs={",
        "deletetexcs=[",
        "directives={",
        "moredirectives={",
        "deletedirectives={",
        "sensitive",
        "alsoletter={",
        "alsodigit={",
        "alsoother={",
        "otherkeywords={",
        "tag=",
        "string=",
        "string=[",
        "morestring=",
        "morestring=[",
        "deletestring=",
        "deletestring=[",
        "comment=",
        "comment=[",
        "morecomment=",
        "morecomment=[",
        "deletecomment=",
        "deletecomment=[",
        "keywordcomment={",
        "morekeywordcomment={",
        "deletekeywordcomment={",
        "keywordcommentsemicolon={",
        "podcomment"
      ],
      "keyvalindex": 0
    },
    "CsCode": {
      "name": "CsCode",
      "detail": "CsCode",
      "snippet": "",
      "option": "",
      "keyvals": [],
      "keyvalindex": -1
    },
    "CsCode[]": {
      "name": "CsCode",
      "detail": "CsCode[]",
      "snippet": "[${1:options}]",
      "option": "",
      "keyvals": [
        "inputpath=",
        "aboveskip=",
        "belowskip=",
        "lineskip=",
        "boxpos=",
        "print",
        "showlines",
        "emptylines=",
        "emptylines=*",
        "gobble=",
        "style=",
        "language=",
        "language=[",
        "alsolanguage=",
        "alsolanguage=[",
        "defaultdialect=[",
        "printpod",
        "usekeywordsintag",
        "tagstyle=",
        "markfirstintag=",
        "makemacrouse",
        "basicstyle=",
        "identifierstyle=",
        "commentstyle=",
        "stringstyle=",
        "keywordstyle=",
        "keywordstyle=[",
        "keywordstyle=[",
        "ndkeywordstyle=",
        "classoffset=",
        "texcsstyle=",
        "texcsstyle=[",
        "texcsstyle=*[",
        "directivestyle=",
        "emph={",
        "emph=[",
        "moreemph={",
        "moreemph=[",
        "deleteemph={",
        "deleteemph=[",
        "emphstyle={",
        "emphstyle=[",
        "delim=[",
        "delim=*[",
        "delim=**[",
        "moredelim=[",
        "moredelim=*[",
        "moredelim=**[",
        "deletedelim=[",
        "deletedelim=*[",
        "deletedelim=**[",
        "extendedchars",
        "inputencoding=",
        "upquote",
        "tabsize=",
        "showtabs",
        "tab=",
        "showspaces",
        "showstringspaces",
        "formfeed=",
        "numbers=",
        "stepnumber=",
        "numberfirstline",
        "numberstyle=",
        "numbersep=",
        "numberblanklines",
        "firstnumber=",
        "name=",
        "title=",
        "caption={",
        "caption={[",
        "label=",
        "nolol",
        "numberbychapter",
        "captionpos=",
        "abovecaptionskip=",
        "belowcaptionskip=",
        "linewidth=",
        "xleftmargin=",
        "xrightmargin=",
        "resetmargins",
        "breaklines",
        "breakatwhitespace",
        "prebreak=",
        "postbreak=",
        "breakindent=",
        "breakautoindent",
        "frame=",
        "frameround=",
        "framesep=",
        "rulesep=",
        "framerule=",
        "framexleftmargin=",
        "framexrightmargin=",
        "framextopmargin=",
        "framexbottommargin=",
        "backgroundcolor=",
        "rulecolor=",
        "fillcolor=",
        "rulesepcolor=",
        "frameshape={",
        "index={",
        "index=[",
        "index=[",
        "moreindex={",
        "moreindex=[",
        "moreindex=[",
        "deleteindex={",
        "deleteindex=[",
        "deleteindex=[",
        "indexstyle=",
        "indexstyle=[",
        "columns=",
        "columns=[",
        "flexiblecolumns",
        "keepspaces",
        "basewidth=",
        "fontadjust",
        "texcl",
        "mathescape",
        "escapechar=",
        "escapeinside=",
        "escapebegin=",
        "escapeend=",
        "fancyvrb",
        "fvcmdparams=",
        "morefvcmdparams=",
        "literate={",
        "literate=*{",
        "rangebeginprefix=",
        "rangebeginsuffix=",
        "rangeendprefix=",
        "rangeendsuffix=",
        "rangeprefix=",
        "rangesuffix=",
        "includerangemarker",
        "multicols=",
        "float",
        "float=",
        "float=*",
        "floatplacement=",
        "firstline=",
        "lastline=",
        "linerange={",
        "consecutivenumbers",
        "keywordsprefix=",
        "keywords={",
        "keywords=[",
        "morekeywords={",
        "morekeywords=[",
        "deletekeywords={",
        "deletekeywords=[",
        "ndkeywords={",
        "moreendkeywords={",
        "deleteendkeywords={",
        "texcs={",
        "texcs=[",
        "moretexcs={",
        "moretexcs=[",
        "deletetexcs={",
        "deletetexcs=[",
        "directives={",
        "moredirectives={",
        "deletedirectives={",
        "sensitive",
        "alsoletter={",
        "alsodigit={",
        "alsoother={",
        "otherkeywords={",
        "tag=",
        "string=",
        "string=[",
        "morestring=",
        "morestring=[",
        "deletestring=",
        "deletestring=[",
        "comment=",
        "comment=[",
        "morecomment=",
        "morecomment=[",
        "deletecomment=",
        "deletecomment=[",
        "keywordcomment={",
        "morekeywordcomment={",
        "deletekeywordcomment={",
        "keywordcommentsemicolon={",
        "podcomment"
      ],
      "keyvalindex": 0
    },
    "CssCode": {
      "name": "CssCode",
      "detail": "CssCode",
      "snippet": "",
      "option": "",
      "keyvals": [],
      "keyvalindex": -1
    },
    "CssCode[]": {
      "name": "CssCode",
      "detail": "CssCode[]",
      "snippet": "[${1:options}]",
      "option": "",
      "keyvals": [
        "inputpath=",
        "aboveskip=",
        "belowskip=",
        "lineskip=",
        "boxpos=",
        "print",
        "showlines",
        "emptylines=",
        "emptylines=*",
        "gobble=",
        "style=",
        "language=",
        "language=[",
        "alsolanguage=",
        "alsolanguage=[",
        "defaultdialect=[",
        "printpod",
        "usekeywordsintag",
        "tagstyle=",
        "markfirstintag=",
        "makemacrouse",
        "basicstyle=",
        "identifierstyle=",
        "commentstyle=",
        "stringstyle=",
        "keywordstyle=",
        "keywordstyle=[",
        "keywordstyle=[",
        "ndkeywordstyle=",
        "classoffset=",
        "texcsstyle=",
        "texcsstyle=[",
        "texcsstyle=*[",
        "directivestyle=",
        "emph={",
        "emph=[",
        "moreemph={",
        "moreemph=[",
        "deleteemph={",
        "deleteemph=[",
        "emphstyle={",
        "emphstyle=[",
        "delim=[",
        "delim=*[",
        "delim=**[",
        "moredelim=[",
        "moredelim=*[",
        "moredelim=**[",
        "deletedelim=[",
        "deletedelim=*[",
        "deletedelim=**[",
        "extendedchars",
        "inputencoding=",
        "upquote",
        "tabsize=",
        "showtabs",
        "tab=",
        "showspaces",
        "showstringspaces",
        "formfeed=",
        "numbers=",
        "stepnumber=",
        "numberfirstline",
        "numberstyle=",
        "numbersep=",
        "numberblanklines",
        "firstnumber=",
        "name=",
        "title=",
        "caption={",
        "caption={[",
        "label=",
        "nolol",
        "numberbychapter",
        "captionpos=",
        "abovecaptionskip=",
        "belowcaptionskip=",
        "linewidth=",
        "xleftmargin=",
        "xrightmargin=",
        "resetmargins",
        "breaklines",
        "breakatwhitespace",
        "prebreak=",
        "postbreak=",
        "breakindent=",
        "breakautoindent",
        "frame=",
        "frameround=",
        "framesep=",
        "rulesep=",
        "framerule=",
        "framexleftmargin=",
        "framexrightmargin=",
        "framextopmargin=",
        "framexbottommargin=",
        "backgroundcolor=",
        "rulecolor=",
        "fillcolor=",
        "rulesepcolor=",
        "frameshape={",
        "index={",
        "index=[",
        "index=[",
        "moreindex={",
        "moreindex=[",
        "moreindex=[",
        "deleteindex={",
        "deleteindex=[",
        "deleteindex=[",
        "indexstyle=",
        "indexstyle=[",
        "columns=",
        "columns=[",
        "flexiblecolumns",
        "keepspaces",
        "basewidth=",
        "fontadjust",
        "texcl",
        "mathescape",
        "escapechar=",
        "escapeinside=",
        "escapebegin=",
        "escapeend=",
        "fancyvrb",
        "fvcmdparams=",
        "morefvcmdparams=",
        "literate={",
        "literate=*{",
        "rangebeginprefix=",
        "rangebeginsuffix=",
        "rangeendprefix=",
        "rangeendsuffix=",
        "rangeprefix=",
        "rangesuffix=",
        "includerangemarker",
        "multicols=",
        "float",
        "float=",
        "float=*",
        "floatplacement=",
        "firstline=",
        "lastline=",
        "linerange={",
        "consecutivenumbers",
        "keywordsprefix=",
        "keywords={",
        "keywords=[",
        "morekeywords={",
        "morekeywords=[",
        "deletekeywords={",
        "deletekeywords=[",
        "ndkeywords={",
        "moreendkeywords={",
        "deleteendkeywords={",
        "texcs={",
        "texcs=[",
        "moretexcs={",
        "moretexcs=[",
        "deletetexcs={",
        "deletetexcs=[",
        "directives={",
        "moredirectives={",
        "deletedirectives={",
        "sensitive",
        "alsoletter={",
        "alsodigit={",
        "alsoother={",
        "otherkeywords={",
        "tag=",
        "string=",
        "string=[",
        "morestring=",
        "morestring=[",
        "deletestring=",
        "deletestring=[",
        "comment=",
        "comment=[",
        "morecomment=",
        "morecomment=[",
        "deletecomment=",
        "deletecomment=[",
        "keywordcomment={",
        "morekeywordcomment={",
        "deletekeywordcomment={",
        "keywordcommentsemicolon={",
        "podcomment"
      ],
      "keyvalindex": 0
    },
    "GenericCode": {
      "name": "GenericCode",
      "detail": "GenericCode",
      "snippet": "",
      "option": "",
      "keyvals": [],
      "keyvalindex": -1
    },
    "GenericCode[]": {
      "name": "GenericCode",
      "detail": "GenericCode[]",
      "snippet": "[${1:options}]",
      "option": "",
      "keyvals": [
        "inputpath=",
        "aboveskip=",
        "belowskip=",
        "lineskip=",
        "boxpos=",
        "print",
        "showlines",
        "emptylines=",
        "emptylines=*",
        "gobble=",
        "style=",
        "language=",
        "language=[",
        "alsolanguage=",
        "alsolanguage=[",
        "defaultdialect=[",
        "printpod",
        "usekeywordsintag",
        "tagstyle=",
        "markfirstintag=",
        "makemacrouse",
        "basicstyle=",
        "identifierstyle=",
        "commentstyle=",
        "stringstyle=",
        "keywordstyle=",
        "keywordstyle=[",
        "keywordstyle=[",
        "ndkeywordstyle=",
        "classoffset=",
        "texcsstyle=",
        "texcsstyle=[",
        "texcsstyle=*[",
        "directivestyle=",
        "emph={",
        "emph=[",
        "moreemph={",
        "moreemph=[",
        "deleteemph={",
        "deleteemph=[",
        "emphstyle={",
        "emphstyle=[",
        "delim=[",
        "delim=*[",
        "delim=**[",
        "moredelim=[",
        "moredelim=*[",
        "moredelim=**[",
        "deletedelim=[",
        "deletedelim=*[",
        "deletedelim=**[",
        "extendedchars",
        "inputencoding=",
        "upquote",
        "tabsize=",
        "showtabs",
        "tab=",
        "showspaces",
        "showstringspaces",
        "formfeed=",
        "numbers=",
        "stepnumber=",
        "numberfirstline",
        "numberstyle=",
        "numbersep=",
        "numberblanklines",
        "firstnumber=",
        "name=",
        "title=",
        "caption={",
        "caption={[",
        "label=",
        "nolol",
        "numberbychapter",
        "captionpos=",
        "abovecaptionskip=",
        "belowcaptionskip=",
        "linewidth=",
        "xleftmargin=",
        "xrightmargin=",
        "resetmargins",
        "breaklines",
        "breakatwhitespace",
        "prebreak=",
        "postbreak=",
        "breakindent=",
        "breakautoindent",
        "frame=",
        "frameround=",
        "framesep=",
        "rulesep=",
        "framerule=",
        "framexleftmargin=",
        "framexrightmargin=",
        "framextopmargin=",
        "framexbottommargin=",
        "backgroundcolor=",
        "rulecolor=",
        "fillcolor=",
        "rulesepcolor=",
        "frameshape={",
        "index={",
        "index=[",
        "index=[",
        "moreindex={",
        "moreindex=[",
        "moreindex=[",
        "deleteindex={",
        "deleteindex=[",
        "deleteindex=[",
        "indexstyle=",
        "indexstyle=[",
        "columns=",
        "columns=[",
        "flexiblecolumns",
        "keepspaces",
        "basewidth=",
        "fontadjust",
        "texcl",
        "mathescape",
        "escapechar=",
        "escapeinside=",
        "escapebegin=",
        "escapeend=",
        "fancyvrb",
        "fvcmdparams=",
        "morefvcmdparams=",
        "literate={",
        "literate=*{",
        "rangebeginprefix=",
        "rangebeginsuffix=",
        "rangeendprefix=",
        "rangeendsuffix=",
        "rangeprefix=",
        "rangesuffix=",
        "includerangemarker",
        "multicols=",
        "float",
        "float=",
        "float=*",
        "floatplacement=",
        "firstline=",
        "lastline=",
        "linerange={",
        "consecutivenumbers",
        "keywordsprefix=",
        "keywords={",
        "keywords=[",
        "morekeywords={",
        "morekeywords=[",
        "deletekeywords={",
        "deletekeywords=[",
        "ndkeywords={",
        "moreendkeywords={",
        "deleteendkeywords={",
        "texcs={",
        "texcs=[",
        "moretexcs={",
        "moretexcs=[",
        "deletetexcs={",
        "deletetexcs=[",
        "directives={",
        "moredirectives={",
        "deletedirectives={",
        "sensitive",
        "alsoletter={",
        "alsodigit={",
        "alsoother={",
        "otherkeywords={",
        "tag=",
        "string=",
        "string=[",
        "morestring=",
        "morestring=[",
        "deletestring=",
        "deletestring=[",
        "comment=",
        "comment=[",
        "morecomment=",
        "morecomment=[",
        "deletecomment=",
        "deletecomment=[",
        "keywordcomment={",
        "morekeywordcomment={",
        "deletekeywordcomment={",
        "keywordcommentsemicolon={",
        "podcomment"
      ],
      "keyvalindex": 0
    },
    "HtmlCode": {
      "name": "HtmlCode",
      "detail": "HtmlCode",
      "snippet": "",
      "option": "",
      "keyvals": [],
      "keyvalindex": -1
    },
    "HtmlCode[]": {
      "name": "HtmlCode",
      "detail": "HtmlCode[]",
      "snippet": "[${1:options}]",
      "option": "",
      "keyvals": [
        "inputpath=",
        "aboveskip=",
        "belowskip=",
        "lineskip=",
        "boxpos=",
        "print",
        "showlines",
        "emptylines=",
        "emptylines=*",
        "gobble=",
        "style=",
        "language=",
        "language=[",
        "alsolanguage=",
        "alsolanguage=[",
        "defaultdialect=[",
        "printpod",
        "usekeywordsintag",
        "tagstyle=",
        "markfirstintag=",
        "makemacrouse",
        "basicstyle=",
        "identifierstyle=",
        "commentstyle=",
        "stringstyle=",
        "keywordstyle=",
        "keywordstyle=[",
        "keywordstyle=[",
        "ndkeywordstyle=",
        "classoffset=",
        "texcsstyle=",
        "texcsstyle=[",
        "texcsstyle=*[",
        "directivestyle=",
        "emph={",
        "emph=[",
        "moreemph={",
        "moreemph=[",
        "deleteemph={",
        "deleteemph=[",
        "emphstyle={",
        "emphstyle=[",
        "delim=[",
        "delim=*[",
        "delim=**[",
        "moredelim=[",
        "moredelim=*[",
        "moredelim=**[",
        "deletedelim=[",
        "deletedelim=*[",
        "deletedelim=**[",
        "extendedchars",
        "inputencoding=",
        "upquote",
        "tabsize=",
        "showtabs",
        "tab=",
        "showspaces",
        "showstringspaces",
        "formfeed=",
        "numbers=",
        "stepnumber=",
        "numberfirstline",
        "numberstyle=",
        "numbersep=",
        "numberblanklines",
        "firstnumber=",
        "name=",
        "title=",
        "caption={",
        "caption={[",
        "label=",
        "nolol",
        "numberbychapter",
        "captionpos=",
        "abovecaptionskip=",
        "belowcaptionskip=",
        "linewidth=",
        "xleftmargin=",
        "xrightmargin=",
        "resetmargins",
        "breaklines",
        "breakatwhitespace",
        "prebreak=",
        "postbreak=",
        "breakindent=",
        "breakautoindent",
        "frame=",
        "frameround=",
        "framesep=",
        "rulesep=",
        "framerule=",
        "framexleftmargin=",
        "framexrightmargin=",
        "framextopmargin=",
        "framexbottommargin=",
        "backgroundcolor=",
        "rulecolor=",
        "fillcolor=",
        "rulesepcolor=",
        "frameshape={",
        "index={",
        "index=[",
        "index=[",
        "moreindex={",
        "moreindex=[",
        "moreindex=[",
        "deleteindex={",
        "deleteindex=[",
        "deleteindex=[",
        "indexstyle=",
        "indexstyle=[",
        "columns=",
        "columns=[",
        "flexiblecolumns",
        "keepspaces",
        "basewidth=",
        "fontadjust",
        "texcl",
        "mathescape",
        "escapechar=",
        "escapeinside=",
        "escapebegin=",
        "escapeend=",
        "fancyvrb",
        "fvcmdparams=",
        "morefvcmdparams=",
        "literate={",
        "literate=*{",
        "rangebeginprefix=",
        "rangebeginsuffix=",
        "rangeendprefix=",
        "rangeendsuffix=",
        "rangeprefix=",
        "rangesuffix=",
        "includerangemarker",
        "multicols=",
        "float",
        "float=",
        "float=*",
        "floatplacement=",
        "firstline=",
        "lastline=",
        "linerange={",
        "consecutivenumbers",
        "keywordsprefix=",
        "keywords={",
        "keywords=[",
        "morekeywords={",
        "morekeywords=[",
        "deletekeywords={",
        "deletekeywords=[",
        "ndkeywords={",
        "moreendkeywords={",
        "deleteendkeywords={",
        "texcs={",
        "texcs=[",
        "moretexcs={",
        "moretexcs=[",
        "deletetexcs={",
        "deletetexcs=[",
        "directives={",
        "moredirectives={",
        "deletedirectives={",
        "sensitive",
        "alsoletter={",
        "alsodigit={",
        "alsoother={",
        "otherkeywords={",
        "tag=",
        "string=",
        "string=[",
        "morestring=",
        "morestring=[",
        "deletestring=",
        "deletestring=[",
        "comment=",
        "comment=[",
        "morecomment=",
        "morecomment=[",
        "deletecomment=",
        "deletecomment=[",
        "keywordcomment={",
        "morekeywordcomment={",
        "deletekeywordcomment={",
        "keywordcommentsemicolon={",
        "podcomment"
      ],
      "keyvalindex": 0
    },
    "JavaCode": {
      "name": "JavaCode",
      "detail": "JavaCode",
      "snippet": "",
      "option": "",
      "keyvals": [],
      "keyvalindex": -1
    },
    "JavaCode[]": {
      "name": "JavaCode",
      "detail": "JavaCode[]",
      "snippet": "[${1:options}]",
      "option": "",
      "keyvals": [
        "inputpath=",
        "aboveskip=",
        "belowskip=",
        "lineskip=",
        "boxpos=",
        "print",
        "showlines",
        "emptylines=",
        "emptylines=*",
        "gobble=",
        "style=",
        "language=",
        "language=[",
        "alsolanguage=",
        "alsolanguage=[",
        "defaultdialect=[",
        "printpod",
        "usekeywordsintag",
        "tagstyle=",
        "markfirstintag=",
        "makemacrouse",
        "basicstyle=",
        "identifierstyle=",
        "commentstyle=",
        "stringstyle=",
        "keywordstyle=",
        "keywordstyle=[",
        "keywordstyle=[",
        "ndkeywordstyle=",
        "classoffset=",
        "texcsstyle=",
        "texcsstyle=[",
        "texcsstyle=*[",
        "directivestyle=",
        "emph={",
        "emph=[",
        "moreemph={",
        "moreemph=[",
        "deleteemph={",
        "deleteemph=[",
        "emphstyle={",
        "emphstyle=[",
        "delim=[",
        "delim=*[",
        "delim=**[",
        "moredelim=[",
        "moredelim=*[",
        "moredelim=**[",
        "deletedelim=[",
        "deletedelim=*[",
        "deletedelim=**[",
        "extendedchars",
        "inputencoding=",
        "upquote",
        "tabsize=",
        "showtabs",
        "tab=",
        "showspaces",
        "showstringspaces",
        "formfeed=",
        "numbers=",
        "stepnumber=",
        "numberfirstline",
        "numberstyle=",
        "numbersep=",
        "numberblanklines",
        "firstnumber=",
        "name=",
        "title=",
        "caption={",
        "caption={[",
        "label=",
        "nolol",
        "numberbychapter",
        "captionpos=",
        "abovecaptionskip=",
        "belowcaptionskip=",
        "linewidth=",
        "xleftmargin=",
        "xrightmargin=",
        "resetmargins",
        "breaklines",
        "breakatwhitespace",
        "prebreak=",
        "postbreak=",
        "breakindent=",
        "breakautoindent",
        "frame=",
        "frameround=",
        "framesep=",
        "rulesep=",
        "framerule=",
        "framexleftmargin=",
        "framexrightmargin=",
        "framextopmargin=",
        "framexbottommargin=",
        "backgroundcolor=",
        "rulecolor=",
        "fillcolor=",
        "rulesepcolor=",
        "frameshape={",
        "index={",
        "index=[",
        "index=[",
        "moreindex={",
        "moreindex=[",
        "moreindex=[",
        "deleteindex={",
        "deleteindex=[",
        "deleteindex=[",
        "indexstyle=",
        "indexstyle=[",
        "columns=",
        "columns=[",
        "flexiblecolumns",
        "keepspaces",
        "basewidth=",
        "fontadjust",
        "texcl",
        "mathescape",
        "escapechar=",
        "escapeinside=",
        "escapebegin=",
        "escapeend=",
        "fancyvrb",
        "fvcmdparams=",
        "morefvcmdparams=",
        "literate={",
        "literate=*{",
        "rangebeginprefix=",
        "rangebeginsuffix=",
        "rangeendprefix=",
        "rangeendsuffix=",
        "rangeprefix=",
        "rangesuffix=",
        "includerangemarker",
        "multicols=",
        "float",
        "float=",
        "float=*",
        "floatplacement=",
        "firstline=",
        "lastline=",
        "linerange={",
        "consecutivenumbers",
        "keywordsprefix=",
        "keywords={",
        "keywords=[",
        "morekeywords={",
        "morekeywords=[",
        "deletekeywords={",
        "deletekeywords=[",
        "ndkeywords={",
        "moreendkeywords={",
        "deleteendkeywords={",
        "texcs={",
        "texcs=[",
        "moretexcs={",
        "moretexcs=[",
        "deletetexcs={",
        "deletetexcs=[",
        "directives={",
        "moredirectives={",
        "deletedirectives={",
        "sensitive",
        "alsoletter={",
        "alsodigit={",
        "alsoother={",
        "otherkeywords={",
        "tag=",
        "string=",
        "string=[",
        "morestring=",
        "morestring=[",
        "deletestring=",
        "deletestring=[",
        "comment=",
        "comment=[",
        "morecomment=",
        "morecomment=[",
        "deletecomment=",
        "deletecomment=[",
        "keywordcomment={",
        "morekeywordcomment={",
        "deletekeywordcomment={",
        "keywordcommentsemicolon={",
        "podcomment"
      ],
      "keyvalindex": 0
    },
    "JsCode": {
      "name": "JsCode",
      "detail": "JsCode",
      "snippet": "",
      "option": "",
      "keyvals": [],
      "keyvalindex": -1
    },
    "JsCode[]": {
      "name": "JsCode",
      "detail": "JsCode[]",
      "snippet": "[${1:options}]",
      "option": "",
      "keyvals": [
        "inputpath=",
        "aboveskip=",
        "belowskip=",
        "lineskip=",
        "boxpos=",
        "print",
        "showlines",
        "emptylines=",
        "emptylines=*",
        "gobble=",
        "style=",
        "language=",
        "language=[",
        "alsolanguage=",
        "alsolanguage=[",
        "defaultdialect=[",
        "printpod",
        "usekeywordsintag",
        "tagstyle=",
        "markfirstintag=",
        "makemacrouse",
        "basicstyle=",
        "identifierstyle=",
        "commentstyle=",
        "stringstyle=",
        "keywordstyle=",
        "keywordstyle=[",
        "keywordstyle=[",
        "ndkeywordstyle=",
        "classoffset=",
        "texcsstyle=",
        "texcsstyle=[",
        "texcsstyle=*[",
        "directivestyle=",
        "emph={",
        "emph=[",
        "moreemph={",
        "moreemph=[",
        "deleteemph={",
        "deleteemph=[",
        "emphstyle={",
        "emphstyle=[",
        "delim=[",
        "delim=*[",
        "delim=**[",
        "moredelim=[",
        "moredelim=*[",
        "moredelim=**[",
        "deletedelim=[",
        "deletedelim=*[",
        "deletedelim=**[",
        "extendedchars",
        "inputencoding=",
        "upquote",
        "tabsize=",
        "showtabs",
        "tab=",
        "showspaces",
        "showstringspaces",
        "formfeed=",
        "numbers=",
        "stepnumber=",
        "numberfirstline",
        "numberstyle=",
        "numbersep=",
        "numberblanklines",
        "firstnumber=",
        "name=",
        "title=",
        "caption={",
        "caption={[",
        "label=",
        "nolol",
        "numberbychapter",
        "captionpos=",
        "abovecaptionskip=",
        "belowcaptionskip=",
        "linewidth=",
        "xleftmargin=",
        "xrightmargin=",
        "resetmargins",
        "breaklines",
        "breakatwhitespace",
        "prebreak=",
        "postbreak=",
        "breakindent=",
        "breakautoindent",
        "frame=",
        "frameround=",
        "framesep=",
        "rulesep=",
        "framerule=",
        "framexleftmargin=",
        "framexrightmargin=",
        "framextopmargin=",
        "framexbottommargin=",
        "backgroundcolor=",
        "rulecolor=",
        "fillcolor=",
        "rulesepcolor=",
        "frameshape={",
        "index={",
        "index=[",
        "index=[",
        "moreindex={",
        "moreindex=[",
        "moreindex=[",
        "deleteindex={",
        "deleteindex=[",
        "deleteindex=[",
        "indexstyle=",
        "indexstyle=[",
        "columns=",
        "columns=[",
        "flexiblecolumns",
        "keepspaces",
        "basewidth=",
        "fontadjust",
        "texcl",
        "mathescape",
        "escapechar=",
        "escapeinside=",
        "escapebegin=",
        "escapeend=",
        "fancyvrb",
        "fvcmdparams=",
        "morefvcmdparams=",
        "literate={",
        "literate=*{",
        "rangebeginprefix=",
        "rangebeginsuffix=",
        "rangeendprefix=",
        "rangeendsuffix=",
        "rangeprefix=",
        "rangesuffix=",
        "includerangemarker",
        "multicols=",
        "float",
        "float=",
        "float=*",
        "floatplacement=",
        "firstline=",
        "lastline=",
        "linerange={",
        "consecutivenumbers",
        "keywordsprefix=",
        "keywords={",
        "keywords=[",
        "morekeywords={",
        "morekeywords=[",
        "deletekeywords={",
        "deletekeywords=[",
        "ndkeywords={",
        "moreendkeywords={",
        "deleteendkeywords={",
        "texcs={",
        "texcs=[",
        "moretexcs={",
        "moretexcs=[",
        "deletetexcs={",
        "deletetexcs=[",
        "directives={",
        "moredirectives={",
        "deletedirectives={",
        "sensitive",
        "alsoletter={",
        "alsodigit={",
        "alsoother={",
        "otherkeywords={",
        "tag=",
        "string=",
        "string=[",
        "morestring=",
        "morestring=[",
        "deletestring=",
        "deletestring=[",
        "comment=",
        "comment=[",
        "morecomment=",
        "morecomment=[",
        "deletecomment=",
        "deletecomment=[",
        "keywordcomment={",
        "morekeywordcomment={",
        "deletekeywordcomment={",
        "keywordcommentsemicolon={",
        "podcomment"
      ],
      "keyvalindex": 0
    },
    "LaTeXCode": {
      "name": "LaTeXCode",
      "detail": "LaTeXCode",
      "snippet": "",
      "option": "",
      "keyvals": [],
      "keyvalindex": -1
    },
    "LaTeXCode[]": {
      "name": "LaTeXCode",
      "detail": "LaTeXCode[]",
      "snippet": "[${1:options}]",
      "option": "",
      "keyvals": [
        "inputpath=",
        "aboveskip=",
        "belowskip=",
        "lineskip=",
        "boxpos=",
        "print",
        "showlines",
        "emptylines=",
        "emptylines=*",
        "gobble=",
        "style=",
        "language=",
        "language=[",
        "alsolanguage=",
        "alsolanguage=[",
        "defaultdialect=[",
        "printpod",
        "usekeywordsintag",
        "tagstyle=",
        "markfirstintag=",
        "makemacrouse",
        "basicstyle=",
        "identifierstyle=",
        "commentstyle=",
        "stringstyle=",
        "keywordstyle=",
        "keywordstyle=[",
        "keywordstyle=[",
        "ndkeywordstyle=",
        "classoffset=",
        "texcsstyle=",
        "texcsstyle=[",
        "texcsstyle=*[",
        "directivestyle=",
        "emph={",
        "emph=[",
        "moreemph={",
        "moreemph=[",
        "deleteemph={",
        "deleteemph=[",
        "emphstyle={",
        "emphstyle=[",
        "delim=[",
        "delim=*[",
        "delim=**[",
        "moredelim=[",
        "moredelim=*[",
        "moredelim=**[",
        "deletedelim=[",
        "deletedelim=*[",
        "deletedelim=**[",
        "extendedchars",
        "inputencoding=",
        "upquote",
        "tabsize=",
        "showtabs",
        "tab=",
        "showspaces",
        "showstringspaces",
        "formfeed=",
        "numbers=",
        "stepnumber=",
        "numberfirstline",
        "numberstyle=",
        "numbersep=",
        "numberblanklines",
        "firstnumber=",
        "name=",
        "title=",
        "caption={",
        "caption={[",
        "label=",
        "nolol",
        "numberbychapter",
        "captionpos=",
        "abovecaptionskip=",
        "belowcaptionskip=",
        "linewidth=",
        "xleftmargin=",
        "xrightmargin=",
        "resetmargins",
        "breaklines",
        "breakatwhitespace",
        "prebreak=",
        "postbreak=",
        "breakindent=",
        "breakautoindent",
        "frame=",
        "frameround=",
        "framesep=",
        "rulesep=",
        "framerule=",
        "framexleftmargin=",
        "framexrightmargin=",
        "framextopmargin=",
        "framexbottommargin=",
        "backgroundcolor=",
        "rulecolor=",
        "fillcolor=",
        "rulesepcolor=",
        "frameshape={",
        "index={",
        "index=[",
        "index=[",
        "moreindex={",
        "moreindex=[",
        "moreindex=[",
        "deleteindex={",
        "deleteindex=[",
        "deleteindex=[",
        "indexstyle=",
        "indexstyle=[",
        "columns=",
        "columns=[",
        "flexiblecolumns",
        "keepspaces",
        "basewidth=",
        "fontadjust",
        "texcl",
        "mathescape",
        "escapechar=",
        "escapeinside=",
        "escapebegin=",
        "escapeend=",
        "fancyvrb",
        "fvcmdparams=",
        "morefvcmdparams=",
        "literate={",
        "literate=*{",
        "rangebeginprefix=",
        "rangebeginsuffix=",
        "rangeendprefix=",
        "rangeendsuffix=",
        "rangeprefix=",
        "rangesuffix=",
        "includerangemarker",
        "multicols=",
        "float",
        "float=",
        "float=*",
        "floatplacement=",
        "firstline=",
        "lastline=",
        "linerange={",
        "consecutivenumbers",
        "keywordsprefix=",
        "keywords={",
        "keywords=[",
        "morekeywords={",
        "morekeywords=[",
        "deletekeywords={",
        "deletekeywords=[",
        "ndkeywords={",
        "moreendkeywords={",
        "deleteendkeywords={",
        "texcs={",
        "texcs=[",
        "moretexcs={",
        "moretexcs=[",
        "deletetexcs={",
        "deletetexcs=[",
        "directives={",
        "moredirectives={",
        "deletedirectives={",
        "sensitive",
        "alsoletter={",
        "alsodigit={",
        "alsoother={",
        "otherkeywords={",
        "tag=",
        "string=",
        "string=[",
        "morestring=",
        "morestring=[",
        "deletestring=",
        "deletestring=[",
        "comment=",
        "comment=[",
        "morecomment=",
        "morecomment=[",
        "deletecomment=",
        "deletecomment=[",
        "keywordcomment={",
        "morekeywordcomment={",
        "deletekeywordcomment={",
        "keywordcommentsemicolon={",
        "podcomment"
      ],
      "keyvalindex": 0
    },
    "ObjCCode": {
      "name": "ObjCCode",
      "detail": "ObjCCode",
      "snippet": "",
      "option": "",
      "keyvals": [],
      "keyvalindex": -1
    },
    "ObjCCode[]": {
      "name": "ObjCCode",
      "detail": "ObjCCode[]",
      "snippet": "[${1:options}]",
      "option": "",
      "keyvals": [
        "inputpath=",
        "aboveskip=",
        "belowskip=",
        "lineskip=",
        "boxpos=",
        "print",
        "showlines",
        "emptylines=",
        "emptylines=*",
        "gobble=",
        "style=",
        "language=",
        "language=[",
        "alsolanguage=",
        "alsolanguage=[",
        "defaultdialect=[",
        "printpod",
        "usekeywordsintag",
        "tagstyle=",
        "markfirstintag=",
        "makemacrouse",
        "basicstyle=",
        "identifierstyle=",
        "commentstyle=",
        "stringstyle=",
        "keywordstyle=",
        "keywordstyle=[",
        "keywordstyle=[",
        "ndkeywordstyle=",
        "classoffset=",
        "texcsstyle=",
        "texcsstyle=[",
        "texcsstyle=*[",
        "directivestyle=",
        "emph={",
        "emph=[",
        "moreemph={",
        "moreemph=[",
        "deleteemph={",
        "deleteemph=[",
        "emphstyle={",
        "emphstyle=[",
        "delim=[",
        "delim=*[",
        "delim=**[",
        "moredelim=[",
        "moredelim=*[",
        "moredelim=**[",
        "deletedelim=[",
        "deletedelim=*[",
        "deletedelim=**[",
        "extendedchars",
        "inputencoding=",
        "upquote",
        "tabsize=",
        "showtabs",
        "tab=",
        "showspaces",
        "showstringspaces",
        "formfeed=",
        "numbers=",
        "stepnumber=",
        "numberfirstline",
        "numberstyle=",
        "numbersep=",
        "numberblanklines",
        "firstnumber=",
        "name=",
        "title=",
        "caption={",
        "caption={[",
        "label=",
        "nolol",
        "numberbychapter",
        "captionpos=",
        "abovecaptionskip=",
        "belowcaptionskip=",
        "linewidth=",
        "xleftmargin=",
        "xrightmargin=",
        "resetmargins",
        "breaklines",
        "breakatwhitespace",
        "prebreak=",
        "postbreak=",
        "breakindent=",
        "breakautoindent",
        "frame=",
        "frameround=",
        "framesep=",
        "rulesep=",
        "framerule=",
        "framexleftmargin=",
        "framexrightmargin=",
        "framextopmargin=",
        "framexbottommargin=",
        "backgroundcolor=",
        "rulecolor=",
        "fillcolor=",
        "rulesepcolor=",
        "frameshape={",
        "index={",
        "index=[",
        "index=[",
        "moreindex={",
        "moreindex=[",
        "moreindex=[",
        "deleteindex={",
        "deleteindex=[",
        "deleteindex=[",
        "indexstyle=",
        "indexstyle=[",
        "columns=",
        "columns=[",
        "flexiblecolumns",
        "keepspaces",
        "basewidth=",
        "fontadjust",
        "texcl",
        "mathescape",
        "escapechar=",
        "escapeinside=",
        "escapebegin=",
        "escapeend=",
        "fancyvrb",
        "fvcmdparams=",
        "morefvcmdparams=",
        "literate={",
        "literate=*{",
        "rangebeginprefix=",
        "rangebeginsuffix=",
        "rangeendprefix=",
        "rangeendsuffix=",
        "rangeprefix=",
        "rangesuffix=",
        "includerangemarker",
        "multicols=",
        "float",
        "float=",
        "float=*",
        "floatplacement=",
        "firstline=",
        "lastline=",
        "linerange={",
        "consecutivenumbers",
        "keywordsprefix=",
        "keywords={",
        "keywords=[",
        "morekeywords={",
        "morekeywords=[",
        "deletekeywords={",
        "deletekeywords=[",
        "ndkeywords={",
        "moreendkeywords={",
        "deleteendkeywords={",
        "texcs={",
        "texcs=[",
        "moretexcs={",
        "moretexcs=[",
        "deletetexcs={",
        "deletetexcs=[",
        "directives={",
        "moredirectives={",
        "deletedirectives={",
        "sensitive",
        "alsoletter={",
        "alsodigit={",
        "alsoother={",
        "otherkeywords={",
        "tag=",
        "string=",
        "string=[",
        "morestring=",
        "morestring=[",
        "deletestring=",
        "deletestring=[",
        "comment=",
        "comment=[",
        "morecomment=",
        "morecomment=[",
        "deletecomment=",
        "deletecomment=[",
        "keywordcomment={",
        "morekeywordcomment={",
        "deletekeywordcomment={",
        "keywordcommentsemicolon={",
        "podcomment"
      ],
      "keyvalindex": 0
    },
    "PhpCode": {
      "name": "PhpCode",
      "detail": "PhpCode",
      "snippet": "",
      "option": "",
      "keyvals": [],
      "keyvalindex": -1
    },
    "PhpCode[]": {
      "name": "PhpCode",
      "detail": "PhpCode[]",
      "snippet": "[${1:options}]",
      "option": "",
      "keyvals": [
        "inputpath=",
        "aboveskip=",
        "belowskip=",
        "lineskip=",
        "boxpos=",
        "print",
        "showlines",
        "emptylines=",
        "emptylines=*",
        "gobble=",
        "style=",
        "language=",
        "language=[",
        "alsolanguage=",
        "alsolanguage=[",
        "defaultdialect=[",
        "printpod",
        "usekeywordsintag",
        "tagstyle=",
        "markfirstintag=",
        "makemacrouse",
        "basicstyle=",
        "identifierstyle=",
        "commentstyle=",
        "stringstyle=",
        "keywordstyle=",
        "keywordstyle=[",
        "keywordstyle=[",
        "ndkeywordstyle=",
        "classoffset=",
        "texcsstyle=",
        "texcsstyle=[",
        "texcsstyle=*[",
        "directivestyle=",
        "emph={",
        "emph=[",
        "moreemph={",
        "moreemph=[",
        "deleteemph={",
        "deleteemph=[",
        "emphstyle={",
        "emphstyle=[",
        "delim=[",
        "delim=*[",
        "delim=**[",
        "moredelim=[",
        "moredelim=*[",
        "moredelim=**[",
        "deletedelim=[",
        "deletedelim=*[",
        "deletedelim=**[",
        "extendedchars",
        "inputencoding=",
        "upquote",
        "tabsize=",
        "showtabs",
        "tab=",
        "showspaces",
        "showstringspaces",
        "formfeed=",
        "numbers=",
        "stepnumber=",
        "numberfirstline",
        "numberstyle=",
        "numbersep=",
        "numberblanklines",
        "firstnumber=",
        "name=",
        "title=",
        "caption={",
        "caption={[",
        "label=",
        "nolol",
        "numberbychapter",
        "captionpos=",
        "abovecaptionskip=",
        "belowcaptionskip=",
        "linewidth=",
        "xleftmargin=",
        "xrightmargin=",
        "resetmargins",
        "breaklines",
        "breakatwhitespace",
        "prebreak=",
        "postbreak=",
        "breakindent=",
        "breakautoindent",
        "frame=",
        "frameround=",
        "framesep=",
        "rulesep=",
        "framerule=",
        "framexleftmargin=",
        "framexrightmargin=",
        "framextopmargin=",
        "framexbottommargin=",
        "backgroundcolor=",
        "rulecolor=",
        "fillcolor=",
        "rulesepcolor=",
        "frameshape={",
        "index={",
        "index=[",
        "index=[",
        "moreindex={",
        "moreindex=[",
        "moreindex=[",
        "deleteindex={",
        "deleteindex=[",
        "deleteindex=[",
        "indexstyle=",
        "indexstyle=[",
        "columns=",
        "columns=[",
        "flexiblecolumns",
        "keepspaces",
        "basewidth=",
        "fontadjust",
        "texcl",
        "mathescape",
        "escapechar=",
        "escapeinside=",
        "escapebegin=",
        "escapeend=",
        "fancyvrb",
        "fvcmdparams=",
        "morefvcmdparams=",
        "literate={",
        "literate=*{",
        "rangebeginprefix=",
        "rangebeginsuffix=",
        "rangeendprefix=",
        "rangeendsuffix=",
        "rangeprefix=",
        "rangesuffix=",
        "includerangemarker",
        "multicols=",
        "float",
        "float=",
        "float=*",
        "floatplacement=",
        "firstline=",
        "lastline=",
        "linerange={",
        "consecutivenumbers",
        "keywordsprefix=",
        "keywords={",
        "keywords=[",
        "morekeywords={",
        "morekeywords=[",
        "deletekeywords={",
        "deletekeywords=[",
        "ndkeywords={",
        "moreendkeywords={",
        "deleteendkeywords={",
        "texcs={",
        "texcs=[",
        "moretexcs={",
        "moretexcs=[",
        "deletetexcs={",
        "deletetexcs=[",
        "directives={",
        "moredirectives={",
        "deletedirectives={",
        "sensitive",
        "alsoletter={",
        "alsodigit={",
        "alsoother={",
        "otherkeywords={",
        "tag=",
        "string=",
        "string=[",
        "morestring=",
        "morestring=[",
        "deletestring=",
        "deletestring=[",
        "comment=",
        "comment=[",
        "morecomment=",
        "morecomment=[",
        "deletecomment=",
        "deletecomment=[",
        "keywordcomment={",
        "morekeywordcomment={",
        "deletekeywordcomment={",
        "keywordcommentsemicolon={",
        "podcomment"
      ],
      "keyvalindex": 0
    },
    "PythonCode": {
      "name": "PythonCode",
      "detail": "PythonCode",
      "snippet": "",
      "option": "",
      "keyvals": [],
      "keyvalindex": -1
    },
    "PythonCode[]": {
      "name": "PythonCode",
      "detail": "PythonCode[]",
      "snippet": "[${1:options}]",
      "option": "",
      "keyvals": [
        "inputpath=",
        "aboveskip=",
        "belowskip=",
        "lineskip=",
        "boxpos=",
        "print",
        "showlines",
        "emptylines=",
        "emptylines=*",
        "gobble=",
        "style=",
        "language=",
        "language=[",
        "alsolanguage=",
        "alsolanguage=[",
        "defaultdialect=[",
        "printpod",
        "usekeywordsintag",
        "tagstyle=",
        "markfirstintag=",
        "makemacrouse",
        "basicstyle=",
        "identifierstyle=",
        "commentstyle=",
        "stringstyle=",
        "keywordstyle=",
        "keywordstyle=[",
        "keywordstyle=[",
        "ndkeywordstyle=",
        "classoffset=",
        "texcsstyle=",
        "texcsstyle=[",
        "texcsstyle=*[",
        "directivestyle=",
        "emph={",
        "emph=[",
        "moreemph={",
        "moreemph=[",
        "deleteemph={",
        "deleteemph=[",
        "emphstyle={",
        "emphstyle=[",
        "delim=[",
        "delim=*[",
        "delim=**[",
        "moredelim=[",
        "moredelim=*[",
        "moredelim=**[",
        "deletedelim=[",
        "deletedelim=*[",
        "deletedelim=**[",
        "extendedchars",
        "inputencoding=",
        "upquote",
        "tabsize=",
        "showtabs",
        "tab=",
        "showspaces",
        "showstringspaces",
        "formfeed=",
        "numbers=",
        "stepnumber=",
        "numberfirstline",
        "numberstyle=",
        "numbersep=",
        "numberblanklines",
        "firstnumber=",
        "name=",
        "title=",
        "caption={",
        "caption={[",
        "label=",
        "nolol",
        "numberbychapter",
        "captionpos=",
        "abovecaptionskip=",
        "belowcaptionskip=",
        "linewidth=",
        "xleftmargin=",
        "xrightmargin=",
        "resetmargins",
        "breaklines",
        "breakatwhitespace",
        "prebreak=",
        "postbreak=",
        "breakindent=",
        "breakautoindent",
        "frame=",
        "frameround=",
        "framesep=",
        "rulesep=",
        "framerule=",
        "framexleftmargin=",
        "framexrightmargin=",
        "framextopmargin=",
        "framexbottommargin=",
        "backgroundcolor=",
        "rulecolor=",
        "fillcolor=",
        "rulesepcolor=",
        "frameshape={",
        "index={",
        "index=[",
        "index=[",
        "moreindex={",
        "moreindex=[",
        "moreindex=[",
        "deleteindex={",
        "deleteindex=[",
        "deleteindex=[",
        "indexstyle=",
        "indexstyle=[",
        "columns=",
        "columns=[",
        "flexiblecolumns",
        "keepspaces",
        "basewidth=",
        "fontadjust",
        "texcl",
        "mathescape",
        "escapechar=",
        "escapeinside=",
        "escapebegin=",
        "escapeend=",
        "fancyvrb",
        "fvcmdparams=",
        "morefvcmdparams=",
        "literate={",
        "literate=*{",
        "rangebeginprefix=",
        "rangebeginsuffix=",
        "rangeendprefix=",
        "rangeendsuffix=",
        "rangeprefix=",
        "rangesuffix=",
        "includerangemarker",
        "multicols=",
        "float",
        "float=",
        "float=*",
        "floatplacement=",
        "firstline=",
        "lastline=",
        "linerange={",
        "consecutivenumbers",
        "keywordsprefix=",
        "keywords={",
        "keywords=[",
        "morekeywords={",
        "morekeywords=[",
        "deletekeywords={",
        "deletekeywords=[",
        "ndkeywords={",
        "moreendkeywords={",
        "deleteendkeywords={",
        "texcs={",
        "texcs=[",
        "moretexcs={",
        "moretexcs=[",
        "deletetexcs={",
        "deletetexcs=[",
        "directives={",
        "moredirectives={",
        "deletedirectives={",
        "sensitive",
        "alsoletter={",
        "alsodigit={",
        "alsoother={",
        "otherkeywords={",
        "tag=",
        "string=",
        "string=[",
        "morestring=",
        "morestring=[",
        "deletestring=",
        "deletestring=[",
        "comment=",
        "comment=[",
        "morecomment=",
        "morecomment=[",
        "deletecomment=",
        "deletecomment=[",
        "keywordcomment={",
        "morekeywordcomment={",
        "deletekeywordcomment={",
        "keywordcommentsemicolon={",
        "podcomment"
      ],
      "keyvalindex": 0
    },
    "SwiftCode": {
      "name": "SwiftCode",
      "detail": "SwiftCode",
      "snippet": "",
      "option": "",
      "keyvals": [],
      "keyvalindex": -1
    },
    "SwiftCode[]": {
      "name": "SwiftCode",
      "detail": "SwiftCode[]",
      "snippet": "[${1:options}]",
      "option": "",
      "keyvals": [
        "inputpath=",
        "aboveskip=",
        "belowskip=",
        "lineskip=",
        "boxpos=",
        "print",
        "showlines",
        "emptylines=",
        "emptylines=*",
        "gobble=",
        "style=",
        "language=",
        "language=[",
        "alsolanguage=",
        "alsolanguage=[",
        "defaultdialect=[",
        "printpod",
        "usekeywordsintag",
        "tagstyle=",
        "markfirstintag=",
        "makemacrouse",
        "basicstyle=",
        "identifierstyle=",
        "commentstyle=",
        "stringstyle=",
        "keywordstyle=",
        "keywordstyle=[",
        "keywordstyle=[",
        "ndkeywordstyle=",
        "classoffset=",
        "texcsstyle=",
        "texcsstyle=[",
        "texcsstyle=*[",
        "directivestyle=",
        "emph={",
        "emph=[",
        "moreemph={",
        "moreemph=[",
        "deleteemph={",
        "deleteemph=[",
        "emphstyle={",
        "emphstyle=[",
        "delim=[",
        "delim=*[",
        "delim=**[",
        "moredelim=[",
        "moredelim=*[",
        "moredelim=**[",
        "deletedelim=[",
        "deletedelim=*[",
        "deletedelim=**[",
        "extendedchars",
        "inputencoding=",
        "upquote",
        "tabsize=",
        "showtabs",
        "tab=",
        "showspaces",
        "showstringspaces",
        "formfeed=",
        "numbers=",
        "stepnumber=",
        "numberfirstline",
        "numberstyle=",
        "numbersep=",
        "numberblanklines",
        "firstnumber=",
        "name=",
        "title=",
        "caption={",
        "caption={[",
        "label=",
        "nolol",
        "numberbychapter",
        "captionpos=",
        "abovecaptionskip=",
        "belowcaptionskip=",
        "linewidth=",
        "xleftmargin=",
        "xrightmargin=",
        "resetmargins",
        "breaklines",
        "breakatwhitespace",
        "prebreak=",
        "postbreak=",
        "breakindent=",
        "breakautoindent",
        "frame=",
        "frameround=",
        "framesep=",
        "rulesep=",
        "framerule=",
        "framexleftmargin=",
        "framexrightmargin=",
        "framextopmargin=",
        "framexbottommargin=",
        "backgroundcolor=",
        "rulecolor=",
        "fillcolor=",
        "rulesepcolor=",
        "frameshape={",
        "index={",
        "index=[",
        "index=[",
        "moreindex={",
        "moreindex=[",
        "moreindex=[",
        "deleteindex={",
        "deleteindex=[",
        "deleteindex=[",
        "indexstyle=",
        "indexstyle=[",
        "columns=",
        "columns=[",
        "flexiblecolumns",
        "keepspaces",
        "basewidth=",
        "fontadjust",
        "texcl",
        "mathescape",
        "escapechar=",
        "escapeinside=",
        "escapebegin=",
        "escapeend=",
        "fancyvrb",
        "fvcmdparams=",
        "morefvcmdparams=",
        "literate={",
        "literate=*{",
        "rangebeginprefix=",
        "rangebeginsuffix=",
        "rangeendprefix=",
        "rangeendsuffix=",
        "rangeprefix=",
        "rangesuffix=",
        "includerangemarker",
        "multicols=",
        "float",
        "float=",
        "float=*",
        "floatplacement=",
        "firstline=",
        "lastline=",
        "linerange={",
        "consecutivenumbers",
        "keywordsprefix=",
        "keywords={",
        "keywords=[",
        "morekeywords={",
        "morekeywords=[",
        "deletekeywords={",
        "deletekeywords=[",
        "ndkeywords={",
        "moreendkeywords={",
        "deleteendkeywords={",
        "texcs={",
        "texcs=[",
        "moretexcs={",
        "moretexcs=[",
        "deletetexcs={",
        "deletetexcs=[",
        "directives={",
        "moredirectives={",
        "deletedirectives={",
        "sensitive",
        "alsoletter={",
        "alsodigit={",
        "alsoother={",
        "otherkeywords={",
        "tag=",
        "string=",
        "string=[",
        "morestring=",
        "morestring=[",
        "deletestring=",
        "deletestring=[",
        "comment=",
        "comment=[",
        "morecomment=",
        "morecomment=[",
        "deletecomment=",
        "deletecomment=[",
        "keywordcomment={",
        "morekeywordcomment={",
        "deletekeywordcomment={",
        "keywordcommentsemicolon={",
        "podcomment"
      ],
      "keyvalindex": 0
    },
    "XmlCode": {
      "name": "XmlCode",
      "detail": "XmlCode",
      "snippet": "",
      "option": "",
      "keyvals": [],
      "keyvalindex": -1
    },
    "XmlCode[]": {
      "name": "XmlCode",
      "detail": "XmlCode[]",
      "snippet": "[${1:options}]",
      "option": "",
      "keyvals": [
        "inputpath=",
        "aboveskip=",
        "belowskip=",
        "lineskip=",
        "boxpos=",
        "print",
        "showlines",
        "emptylines=",
        "emptylines=*",
        "gobble=",
        "style=",
        "language=",
        "language=[",
        "alsolanguage=",
        "alsolanguage=[",
        "defaultdialect=[",
        "printpod",
        "usekeywordsintag",
        "tagstyle=",
        "markfirstintag=",
        "makemacrouse",
        "basicstyle=",
        "identifierstyle=",
        "commentstyle=",
        "stringstyle=",
        "keywordstyle=",
        "keywordstyle=[",
        "keywordstyle=[",
        "ndkeywordstyle=",
        "classoffset=",
        "texcsstyle=",
        "texcsstyle=[",
        "texcsstyle=*[",
        "directivestyle=",
        "emph={",
        "emph=[",
        "moreemph={",
        "moreemph=[",
        "deleteemph={",
        "deleteemph=[",
        "emphstyle={",
        "emphstyle=[",
        "delim=[",
        "delim=*[",
        "delim=**[",
        "moredelim=[",
        "moredelim=*[",
        "moredelim=**[",
        "deletedelim=[",
        "deletedelim=*[",
        "deletedelim=**[",
        "extendedchars",
        "inputencoding=",
        "upquote",
        "tabsize=",
        "showtabs",
        "tab=",
        "showspaces",
        "showstringspaces",
        "formfeed=",
        "numbers=",
        "stepnumber=",
        "numberfirstline",
        "numberstyle=",
        "numbersep=",
        "numberblanklines",
        "firstnumber=",
        "name=",
        "title=",
        "caption={",
        "caption={[",
        "label=",
        "nolol",
        "numberbychapter",
        "captionpos=",
        "abovecaptionskip=",
        "belowcaptionskip=",
        "linewidth=",
        "xleftmargin=",
        "xrightmargin=",
        "resetmargins",
        "breaklines",
        "breakatwhitespace",
        "prebreak=",
        "postbreak=",
        "breakindent=",
        "breakautoindent",
        "frame=",
        "frameround=",
        "framesep=",
        "rulesep=",
        "framerule=",
        "framexleftmargin=",
        "framexrightmargin=",
        "framextopmargin=",
        "framexbottommargin=",
        "backgroundcolor=",
        "rulecolor=",
        "fillcolor=",
        "rulesepcolor=",
        "frameshape={",
        "index={",
        "index=[",
        "index=[",
        "moreindex={",
        "moreindex=[",
        "moreindex=[",
        "deleteindex={",
        "deleteindex=[",
        "deleteindex=[",
        "indexstyle=",
        "indexstyle=[",
        "columns=",
        "columns=[",
        "flexiblecolumns",
        "keepspaces",
        "basewidth=",
        "fontadjust",
        "texcl",
        "mathescape",
        "escapechar=",
        "escapeinside=",
        "escapebegin=",
        "escapeend=",
        "fancyvrb",
        "fvcmdparams=",
        "morefvcmdparams=",
        "literate={",
        "literate=*{",
        "rangebeginprefix=",
        "rangebeginsuffix=",
        "rangeendprefix=",
        "rangeendsuffix=",
        "rangeprefix=",
        "rangesuffix=",
        "includerangemarker",
        "multicols=",
        "float",
        "float=",
        "float=*",
        "floatplacement=",
        "firstline=",
        "lastline=",
        "linerange={",
        "consecutivenumbers",
        "keywordsprefix=",
        "keywords={",
        "keywords=[",
        "morekeywords={",
        "morekeywords=[",
        "deletekeywords={",
        "deletekeywords=[",
        "ndkeywords={",
        "moreendkeywords={",
        "deleteendkeywords={",
        "texcs={",
        "texcs=[",
        "moretexcs={",
        "moretexcs=[",
        "deletetexcs={",
        "deletetexcs=[",
        "directives={",
        "moredirectives={",
        "deletedirectives={",
        "sensitive",
        "alsoletter={",
        "alsodigit={",
        "alsoother={",
        "otherkeywords={",
        "tag=",
        "string=",
        "string=[",
        "morestring=",
        "morestring=[",
        "deletestring=",
        "deletestring=[",
        "comment=",
        "comment=[",
        "morecomment=",
        "morecomment=[",
        "deletecomment=",
        "deletecomment=[",
        "keywordcomment={",
        "morekeywordcomment={",
        "deletekeywordcomment={",
        "keywordcommentsemicolon={",
        "podcomment"
      ],
      "keyvalindex": 0
    }
  },
  "options": []
}