{
  "includes": [],
  "cmds": {
    "IEEEauthorrefmark{}": {
      "command": "IEEEauthorrefmark{}",
      "snippet": "IEEEauthorrefmark{${1:mark}}",
      "option": "",
      "keyvals": [],
      "keyvalindex": -1
    },
    "IEEEPARstart{}{}": {
      "command": "IEEEPARstart{}{}",
      "snippet": "IEEEPARstart{${1:letter}}{${2:text%plain}}",
      "option": "",
      "keyvals": [],
      "keyvalindex": -1
    },
    "IEEEPARstartCAPSTYLE": {
      "command": "IEEEPARstartCAPSTYLE",
      "snippet": "IEEEPARstartCAPSTYLE",
      "option": "",
      "keyvals": [],
      "keyvalindex": -1
    },
    "IEEEPARstartDROPDEPTH": {
      "command": "IEEEPARstartDROPDEPTH",
      "snippet": "IEEEPARstartDROPDEPTH",
      "option": "",
      "keyvals": [],
      "keyvalindex": -1
    },
    "IEEEPARstartDROPLINES": {
      "command": "IEEEPARstartDROPLINES",
      "snippet": "IEEEPARstartDROPLINES",
      "option": "",
      "keyvals": [],
      "keyvalindex": -1
    },
    "IEEEPARstartFONTSTYLE": {
      "command": "IEEEPARstartFONTSTYLE",
      "snippet": "IEEEPARstartFONTSTYLE",
      "option": "",
      "keyvals": [],
      "keyvalindex": -1
    },
    "IEEEPARstartHEIGHTTEXT": {
      "command": "IEEEPARstartHEIGHTTEXT",
      "snippet": "IEEEPARstartHEIGHTTEXT",
      "option": "",
      "keyvals": [],
      "keyvalindex": -1
    },
    "IEEEPARstartHOFFSET": {
      "command": "IEEEPARstartHOFFSET",
      "snippet": "IEEEPARstartHOFFSET",
      "option": "",
      "keyvals": [],
      "keyvalindex": -1
    },
    "IEEEPARstartITLCORRECT": {
      "command": "IEEEPARstartITLCORRECT",
      "snippet": "IEEEPARstartITLCORRECT",
      "option": "",
      "keyvals": [],
      "keyvalindex": -1
    },
    "IEEEPARstartMINPAGELINES": {
      "command": "IEEEPARstartMINPAGELINES",
      "snippet": "IEEEPARstartMINPAGELINES",
      "option": "",
      "keyvals": [],
      "keyvalindex": -1
    },
    "IEEEPARstartSEP": {
      "command": "IEEEPARstartSEP",
      "snippet": "IEEEPARstartSEP",
      "option": "",
      "keyvals": [],
      "keyvalindex": -1
    },
    "IEEEPARstartWORDCAPSTYLE": {
      "command": "IEEEPARstartWORDCAPSTYLE",
      "snippet": "IEEEPARstartWORDCAPSTYLE",
      "option": "",
      "keyvals": [],
      "keyvalindex": -1
    },
    "IEEEPARstartWORDFONTSTYLE": {
      "command": "IEEEPARstartWORDFONTSTYLE",
      "snippet": "IEEEPARstartWORDFONTSTYLE",
      "option": "",
      "keyvals": [],
      "keyvalindex": -1
    },
    "IEEEproofindentspace": {
      "command": "IEEEproofindentspace",
      "snippet": "IEEEproofindentspace",
      "option": "",
      "keyvals": [],
      "keyvalindex": -1
    },
    "IEEEproofname": {
      "command": "IEEEproofname",
      "snippet": "IEEEproofname",
      "option": "",
      "keyvals": [],
      "keyvalindex": -1
    },
    "IEEEQED": {
      "command": "IEEEQED",
      "snippet": "IEEEQED",
      "option": "",
      "keyvals": [],
      "keyvalindex": -1
    },
    "IEEEQEDhere": {
      "command": "IEEEQEDhere",
      "snippet": "IEEEQEDhere",
      "option": "",
      "keyvals": [],
      "keyvalindex": -1
    },
    "IEEEQEDhereeqn": {
      "command": "IEEEQEDhereeqn",
      "snippet": "IEEEQEDhereeqn",
      "option": "",
      "keyvals": [],
      "keyvalindex": -1
    },
    "IEEEQEDclosed": {
      "command": "IEEEQEDclosed",
      "snippet": "IEEEQEDclosed",
      "option": "",
      "keyvals": [],
      "keyvalindex": -1
    },
    "IEEEQEDopen": {
      "command": "IEEEQEDopen",
      "snippet": "IEEEQEDopen",
      "option": "",
      "keyvals": [],
      "keyvalindex": -1
    },
    "IEEEQEDoff": {
      "command": "IEEEQEDoff",
      "snippet": "IEEEQEDoff",
      "option": "",
      "keyvals": [],
      "keyvalindex": -1
    },
    "IEEEsetlabelwidth{}": {
      "command": "IEEEsetlabelwidth{}",
      "snippet": "IEEEsetlabelwidth{${1:argument}}",
      "option": "",
      "keyvals": [],
      "keyvalindex": -1
    },
    "IEEEilabelindentA": {
      "command": "IEEEilabelindentA",
      "snippet": "IEEEilabelindentA",
      "option": "",
      "keyvals": [],
      "keyvalindex": -1
    },
    "IEEEilabelindentB": {
      "command": "IEEEilabelindentB",
      "snippet": "IEEEilabelindentB",
      "option": "",
      "keyvals": [],
      "keyvalindex": -1
    },
    "IEEEilabelindent": {
      "command": "IEEEilabelindent",
      "snippet": "IEEEilabelindent",
      "option": "",
      "keyvals": [],
      "keyvalindex": -1
    },
    "IEEEelabelindent": {
      "command": "IEEEelabelindent",
      "snippet": "IEEEelabelindent",
      "option": "",
      "keyvals": [],
      "keyvalindex": -1
    },
    "IEEEdlabelindent": {
      "command": "IEEEdlabelindent",
      "snippet": "IEEEdlabelindent",
      "option": "",
      "keyvals": [],
      "keyvalindex": -1
    },
    "IEEElabelindent": {
      "command": "IEEElabelindent",
      "snippet": "IEEElabelindent",
      "option": "",
      "keyvals": [],
      "keyvalindex": -1
    },
    "IEEElabelindentfactori": {
      "command": "IEEElabelindentfactori",
      "snippet": "IEEElabelindentfactori",
      "option": "",
      "keyvals": [],
      "keyvalindex": -1
    },
    "IEEElabelindentfactorii": {
      "command": "IEEElabelindentfactorii",
      "snippet": "IEEElabelindentfactorii",
      "option": "",
      "keyvals": [],
      "keyvalindex": -1
    },
    "IEEElabelindentfactoriii": {
      "command": "IEEElabelindentfactoriii",
      "snippet": "IEEElabelindentfactoriii",
      "option": "",
      "keyvals": [],
      "keyvalindex": -1
    },
    "IEEElabelindentfactoriv": {
      "command": "IEEElabelindentfactoriv",
      "snippet": "IEEElabelindentfactoriv",
      "option": "",
      "keyvals": [],
      "keyvalindex": -1
    },
    "IEEElabelindentfactorv": {
      "command": "IEEElabelindentfactorv",
      "snippet": "IEEElabelindentfactorv",
      "option": "",
      "keyvals": [],
      "keyvalindex": -1
    },
    "IEEElabelindentfactorvi": {
      "command": "IEEElabelindentfactorvi",
      "snippet": "IEEElabelindentfactorvi",
      "option": "",
      "keyvals": [],
      "keyvalindex": -1
    },
    "IEEElabelindentfactor": {
      "command": "IEEElabelindentfactor",
      "snippet": "IEEElabelindentfactor",
      "option": "",
      "keyvals": [],
      "keyvalindex": -1
    },
    "IEEEiednormlabelsep": {
      "command": "IEEEiednormlabelsep",
      "snippet": "IEEEiednormlabelsep",
      "option": "",
      "keyvals": [],
      "keyvalindex": -1
    },
    "IEEEiedmathlabelsep": {
      "command": "IEEEiedmathlabelsep",
      "snippet": "IEEEiedmathlabelsep",
      "option": "",
      "keyvals": [],
      "keyvalindex": -1
    },
    "IEEEiedtopsep": {
      "command": "IEEEiedtopsep",
      "snippet": "IEEEiedtopsep",
      "option": "",
      "keyvals": [],
      "keyvalindex": -1
    },
    "IEEEiedlistdecl": {
      "command": "IEEEiedlistdecl",
      "snippet": "IEEEiedlistdecl",
      "option": "",
      "keyvals": [],
      "keyvalindex": -1
    },
    "ifIEEEnolabelindentfactor": {
      "command": "ifIEEEnolabelindentfactor",
      "snippet": "ifIEEEnolabelindentfactor",
      "option": "",
      "keyvals": [],
      "keyvalindex": -1
    },
    "IEEEnolabelindentfactortrue": {
      "command": "IEEEnolabelindentfactortrue",
      "snippet": "IEEEnolabelindentfactortrue",
      "option": "",
      "keyvals": [],
      "keyvalindex": -1
    },
    "IEEEnolabelindentfactorfalse": {
      "command": "IEEEnolabelindentfactorfalse",
      "snippet": "IEEEnolabelindentfactorfalse",
      "option": "",
      "keyvals": [],
      "keyvalindex": -1
    },
    "ifIEEEnocalcleftmargin": {
      "command": "ifIEEEnocalcleftmargin",
      "snippet": "ifIEEEnocalcleftmargin",
      "option": "",
      "keyvals": [],
      "keyvalindex": -1
    },
    "IEEEnocalcleftmargintrue": {
      "command": "IEEEnocalcleftmargintrue",
      "snippet": "IEEEnocalcleftmargintrue",
      "option": "",
      "keyvals": [],
      "keyvalindex": -1
    },
    "IEEEnocalcleftmarginfalse": {
      "command": "IEEEnocalcleftmarginfalse",
      "snippet": "IEEEnocalcleftmarginfalse",
      "option": "",
      "keyvals": [],
      "keyvalindex": -1
    },
    "IEEEusemathlabelsep": {
      "command": "IEEEusemathlabelsep",
      "snippet": "IEEEusemathlabelsep",
      "option": "",
      "keyvals": [],
      "keyvalindex": -1
    },
    "IEEEiedlabeljustifyl": {
      "command": "IEEEiedlabeljustifyl",
      "snippet": "IEEEiedlabeljustifyl",
      "option": "",
      "keyvals": [],
      "keyvalindex": -1
    },
    "IEEEiedlabeljustifyc": {
      "command": "IEEEiedlabeljustifyc",
      "snippet": "IEEEiedlabeljustifyc",
      "option": "",
      "keyvals": [],
      "keyvalindex": -1
    },
    "IEEEiedlabeljustifyr": {
      "command": "IEEEiedlabeljustifyr",
      "snippet": "IEEEiedlabeljustifyr",
      "option": "",
      "keyvals": [],
      "keyvalindex": -1
    },
    "IEEEeqnarraynumspace": {
      "command": "IEEEeqnarraynumspace",
      "snippet": "IEEEeqnarraynumspace",
      "option": "",
      "keyvals": [],
      "keyvalindex": -1
    },
    "IEEEeqnarraydefcol{}{}{}": {
      "command": "IEEEeqnarraydefcol{}{}{}",
      "snippet": "IEEEeqnarraydefcol{${1:col id}}{${2:predef%definition}}{${3:postdef%definition}}",
      "option": "",
      "keyvals": [],
      "keyvalindex": -1
    },
    "IEEEeqnarraydefcolsep{}{}": {
      "command": "IEEEeqnarraydefcolsep{}{}",
      "snippet": "IEEEeqnarraydefcolsep{${1:colsep id}}{${2:definition}}",
      "option": "",
      "keyvals": [],
      "keyvalindex": -1
    },
    "yesnumber": {
      "command": "yesnumber",
      "snippet": "yesnumber",
      "option": "",
      "keyvals": [],
      "keyvalindex": -1
    },
    "IEEEyesnumber": {
      "command": "IEEEyesnumber",
      "snippet": "IEEEyesnumber",
      "option": "",
      "keyvals": [],
      "keyvalindex": -1
    },
    "IEEEyesnumber*": {
      "command": "IEEEyesnumber*",
      "snippet": "IEEEyesnumber*",
      "option": "",
      "keyvals": [],
      "keyvalindex": -1
    },
    "IEEEyessubnumber": {
      "command": "IEEEyessubnumber",
      "snippet": "IEEEyessubnumber",
      "option": "",
      "keyvals": [],
      "keyvalindex": -1
    },
    "IEEEyessubnumber*": {
      "command": "IEEEyessubnumber*",
      "snippet": "IEEEyessubnumber*",
      "option": "",
      "keyvals": [],
      "keyvalindex": -1
    },
    "IEEEnonumber": {
      "command": "IEEEnonumber",
      "snippet": "IEEEnonumber",
      "option": "",
      "keyvals": [],
      "keyvalindex": -1
    },
    "IEEEnonumber*": {
      "command": "IEEEnonumber*",
      "snippet": "IEEEnonumber*",
      "option": "",
      "keyvals": [],
      "keyvalindex": -1
    },
    "IEEEnosubnumber": {
      "command": "IEEEnosubnumber",
      "snippet": "IEEEnosubnumber",
      "option": "",
      "keyvals": [],
      "keyvalindex": -1
    },
    "IEEEnosubnumber*": {
      "command": "IEEEnosubnumber*",
      "snippet": "IEEEnosubnumber*",
      "option": "",
      "keyvals": [],
      "keyvalindex": -1
    },
    "theIEEEsubequation": {
      "command": "theIEEEsubequation",
      "snippet": "theIEEEsubequation",
      "option": "",
      "keyvals": [],
      "keyvalindex": -1
    },
    "theIEEEsubequationdis": {
      "command": "theIEEEsubequationdis",
      "snippet": "theIEEEsubequationdis",
      "option": "",
      "keyvals": [],
      "keyvalindex": -1
    },
    "theequationdis": {
      "command": "theequationdis",
      "snippet": "theequationdis",
      "option": "",
      "keyvals": [],
      "keyvalindex": -1
    },
    "theHequation": {
      "command": "theHequation",
      "snippet": "theHequation",
      "option": "",
      "keyvals": [],
      "keyvalindex": -1
    },
    "IEEEeqnarraymathstyle": {
      "command": "IEEEeqnarraymathstyle",
      "snippet": "IEEEeqnarraymathstyle",
      "option": "",
      "keyvals": [],
      "keyvalindex": -1
    },
    "IEEEeqnarraytextstyle": {
      "command": "IEEEeqnarraytextstyle",
      "snippet": "IEEEeqnarraytextstyle",
      "option": "",
      "keyvals": [],
      "keyvalindex": -1
    },
    "IEEEeqnarraydecl": {
      "command": "IEEEeqnarraydecl",
      "snippet": "IEEEeqnarraydecl",
      "option": "",
      "keyvals": [],
      "keyvalindex": -1
    },
    "IEEEeqnarrayboxdecl": {
      "command": "IEEEeqnarrayboxdecl",
      "snippet": "IEEEeqnarrayboxdecl",
      "option": "",
      "keyvals": [],
      "keyvalindex": -1
    },
    "IEEEnormaljot": {
      "command": "IEEEnormaljot",
      "snippet": "IEEEnormaljot",
      "option": "",
      "keyvals": [],
      "keyvalindex": -1
    },
    "IEEEeqnarraystrutsize{}{}": {
      "command": "IEEEeqnarraystrutsize{}{}",
      "snippet": "IEEEeqnarraystrutsize{${1:height}}{${2:depth}}",
      "option": "",
      "keyvals": [],
      "keyvalindex": -1
    },
    "IEEEeqnarraystrutsize{}{}[]": {
      "command": "IEEEeqnarraystrutsize{}{}[]",
      "snippet": "IEEEeqnarraystrutsize{${1:height}}{${2:depth}}[${3:decl}]",
      "option": "",
      "keyvals": [],
      "keyvalindex": -1
    },
    "IEEEeqnarraystrutsizeadd{}{}": {
      "command": "IEEEeqnarraystrutsizeadd{}{}",
      "snippet": "IEEEeqnarraystrutsizeadd{${1:height}}{${2:depth}}",
      "option": "",
      "keyvals": [],
      "keyvalindex": -1
    },
    "IEEEeqnarraystrutsizeadd{}{}[]": {
      "command": "IEEEeqnarraystrutsizeadd{}{}[]",
      "snippet": "IEEEeqnarraystrutsizeadd{${1:height}}{${2:depth}}[${3:decl}]",
      "option": "",
      "keyvals": [],
      "keyvalindex": -1
    },
    "IEEEstrut": {
      "command": "IEEEstrut",
      "snippet": "IEEEstrut",
      "option": "",
      "keyvals": [],
      "keyvalindex": -1
    },
    "IEEEstrut[]": {
      "command": "IEEEstrut[]",
      "snippet": "IEEEstrut[${1:height}]",
      "option": "",
      "keyvals": [],
      "keyvalindex": -1
    },
    "IEEEstrut[][]": {
      "command": "IEEEstrut[][]",
      "snippet": "IEEEstrut[${1:height}][${2:depth}]",
      "option": "",
      "keyvals": [],
      "keyvalindex": -1
    },
    "IEEEstrut[][][]": {
      "command": "IEEEstrut[][][]",
      "snippet": "IEEEstrut[${1:height}][${2:depth}][${3:decl}]",
      "option": "",
      "keyvals": [],
      "keyvalindex": -1
    },
    "ifIEEEvisiblestruts": {
      "command": "ifIEEEvisiblestruts",
      "snippet": "ifIEEEvisiblestruts",
      "option": "",
      "keyvals": [],
      "keyvalindex": -1
    },
    "IEEEvisiblestrutstrue": {
      "command": "IEEEvisiblestrutstrue",
      "snippet": "IEEEvisiblestrutstrue",
      "option": "",
      "keyvals": [],
      "keyvalindex": -1
    },
    "IEEEvisiblestrutsfalse": {
      "command": "IEEEvisiblestrutsfalse",
      "snippet": "IEEEvisiblestrutsfalse",
      "option": "",
      "keyvals": [],
      "keyvalindex": -1
    },
    "IEEEeqnarraystrutmode": {
      "command": "IEEEeqnarraystrutmode",
      "snippet": "IEEEeqnarraystrutmode",
      "option": "",
      "keyvals": [],
      "keyvalindex": -1
    },
    "IEEEeqnarraymulticol{}{}{}": {
      "command": "IEEEeqnarraymulticol{}{}{}",
      "snippet": "IEEEeqnarraymulticol{${1:num cols}}{${2:col type}}{${3:text}}",
      "option": "",
      "keyvals": [],
      "keyvalindex": -1
    },
    "IEEEeqnarrayomit": {
      "command": "IEEEeqnarrayomit",
      "snippet": "IEEEeqnarrayomit",
      "option": "",
      "keyvals": [],
      "keyvalindex": -1
    },
    "IEEEeqnarrayvrule": {
      "command": "IEEEeqnarrayvrule",
      "snippet": "IEEEeqnarrayvrule",
      "option": "",
      "keyvals": [],
      "keyvalindex": -1
    },
    "IEEEeqnarrayvrule[]": {
      "command": "IEEEeqnarrayvrule[]",
      "snippet": "IEEEeqnarrayvrule[${1:thickness%l}]",
      "option": "",
      "keyvals": [],
      "keyvalindex": -1
    },
    "IEEEeqnarrayseprow": {
      "command": "IEEEeqnarrayseprow",
      "snippet": "IEEEeqnarrayseprow",
      "option": "",
      "keyvals": [],
      "keyvalindex": -1
    },
    "IEEEeqnarrayseprow[]": {
      "command": "IEEEeqnarrayseprow[]",
      "snippet": "IEEEeqnarrayseprow[${1:height}]",
      "option": "",
      "keyvals": [],
      "keyvalindex": -1
    },
    "IEEEeqnarrayseprow[][]": {
      "command": "IEEEeqnarrayseprow[][]",
      "snippet": "IEEEeqnarrayseprow[${1:height}][${2:decl}]",
      "option": "",
      "keyvals": [],
      "keyvalindex": -1
    },
    "IEEEeqnarrayseprowcut": {
      "command": "IEEEeqnarrayseprowcut",
      "snippet": "IEEEeqnarrayseprowcut",
      "option": "",
      "keyvals": [],
      "keyvalindex": -1
    },
    "IEEEeqnarrayseprowcut[]": {
      "command": "IEEEeqnarrayseprowcut[]",
      "snippet": "IEEEeqnarrayseprowcut[${1:height}]",
      "option": "",
      "keyvals": [],
      "keyvalindex": -1
    },
    "IEEEeqnarrayseprowcut[][]": {
      "command": "IEEEeqnarrayseprowcut[][]",
      "snippet": "IEEEeqnarrayseprowcut[${1:height}][${2:decl}]",
      "option": "",
      "keyvals": [],
      "keyvalindex": -1
    },
    "IEEEeqnarrayrulerow": {
      "command": "IEEEeqnarrayrulerow",
      "snippet": "IEEEeqnarrayrulerow",
      "option": "",
      "keyvals": [],
      "keyvalindex": -1
    },
    "IEEEeqnarrayrulerow[]": {
      "command": "IEEEeqnarrayrulerow[]",
      "snippet": "IEEEeqnarrayrulerow[${1:thickness%l}]",
      "option": "",
      "keyvals": [],
      "keyvalindex": -1
    },
    "IEEEeqnarraydblrulerow": {
      "command": "IEEEeqnarraydblrulerow",
      "snippet": "IEEEeqnarraydblrulerow",
      "option": "",
      "keyvals": [],
      "keyvalindex": -1
    },
    "IEEEeqnarraydblrulerow[]": {
      "command": "IEEEeqnarraydblrulerow[]",
      "snippet": "IEEEeqnarraydblrulerow[${1:thickness%l}]",
      "option": "",
      "keyvals": [],
      "keyvalindex": -1
    },
    "IEEEeqnarraydblrulerow[][]": {
      "command": "IEEEeqnarraydblrulerow[][]",
      "snippet": "IEEEeqnarraydblrulerow[${1:thickness%l}][${2:spacing}]",
      "option": "",
      "keyvals": [],
      "keyvalindex": -1
    },
    "IEEEeqnarraydblrulerowcut": {
      "command": "IEEEeqnarraydblrulerowcut",
      "snippet": "IEEEeqnarraydblrulerowcut",
      "option": "",
      "keyvals": [],
      "keyvalindex": -1
    },
    "IEEEeqnarraydblrulerowcut[]": {
      "command": "IEEEeqnarraydblrulerowcut[]",
      "snippet": "IEEEeqnarraydblrulerowcut[${1:thickness%l}]",
      "option": "",
      "keyvals": [],
      "keyvalindex": -1
    },
    "IEEEeqnarraydblrulerowcut[][]": {
      "command": "IEEEeqnarraydblrulerowcut[][]",
      "snippet": "IEEEeqnarraydblrulerowcut[${1:thickness%l}][${2:spacing}]",
      "option": "",
      "keyvals": [],
      "keyvalindex": -1
    },
    "bstctlcite{}": {
      "command": "bstctlcite{}",
      "snippet": "bstctlcite{${1:bibid}}",
      "option": "",
      "keyvals": [],
      "keyvalindex": -1
    },
    "bstctlcite[]{}": {
      "command": "bstctlcite[]{}",
      "snippet": "bstctlcite[${2:aux spec}]{${1:bibid}}",
      "option": "",
      "keyvals": [],
      "keyvalindex": -1
    },
    "IEEEnoauxwrite{}": {
      "command": "IEEEnoauxwrite{}",
      "snippet": "IEEEnoauxwrite{${1:commands}}",
      "option": "",
      "keyvals": [],
      "keyvalindex": -1
    },
    "IEEEcalcleftmargin{}": {
      "command": "IEEEcalcleftmargin{}",
      "snippet": "IEEEcalcleftmargin{${1:width}}",
      "option": "",
      "keyvals": [],
      "keyvalindex": -1
    },
    "IEEEdefaultfootersampletext": {
      "command": "IEEEdefaultfootersampletext",
      "snippet": "IEEEdefaultfootersampletext",
      "option": "",
      "keyvals": [],
      "keyvalindex": -1
    },
    "IEEEdefaultheadersampletext": {
      "command": "IEEEdefaultheadersampletext",
      "snippet": "IEEEdefaultheadersampletext",
      "option": "",
      "keyvals": [],
      "keyvalindex": -1
    },
    "IEEEdefaultsampletext": {
      "command": "IEEEdefaultsampletext",
      "snippet": "IEEEdefaultsampletext",
      "option": "",
      "keyvals": [],
      "keyvalindex": -1
    },
    "IEEEnormalcatcodes": {
      "command": "IEEEnormalcatcodes",
      "snippet": "IEEEnormalcatcodes",
      "option": "",
      "keyvals": [],
      "keyvalindex": -1
    },
    "IEEEnormalcatcodesnum": {
      "command": "IEEEnormalcatcodesnum",
      "snippet": "IEEEnormalcatcodesnum",
      "option": "",
      "keyvals": [],
      "keyvalindex": -1
    },
    "IEEEnormalcatcodespunct": {
      "command": "IEEEnormalcatcodespunct",
      "snippet": "IEEEnormalcatcodespunct",
      "option": "",
      "keyvals": [],
      "keyvalindex": -1
    },
    "IEEEPARstartletwidth": {
      "command": "IEEEPARstartletwidth",
      "snippet": "IEEEPARstartletwidth",
      "option": "",
      "keyvals": [],
      "keyvalindex": -1
    },
    "IEEEquantizedlength": {
      "command": "IEEEquantizedlength",
      "snippet": "IEEEquantizedlength",
      "option": "",
      "keyvals": [],
      "keyvalindex": -1
    },
    "IEEEquantizedlengthdiff": {
      "command": "IEEEquantizedlengthdiff",
      "snippet": "IEEEquantizedlengthdiff",
      "option": "",
      "keyvals": [],
      "keyvalindex": -1
    },
    "IEEEquantizedlengthint": {
      "command": "IEEEquantizedlengthint",
      "snippet": "IEEEquantizedlengthint",
      "option": "",
      "keyvals": [],
      "keyvalindex": -1
    },
    "IEEEquantizedtextheightdiff": {
      "command": "IEEEquantizedtextheightdiff",
      "snippet": "IEEEquantizedtextheightdiff",
      "option": "",
      "keyvals": [],
      "keyvalindex": -1
    },
    "IEEEquantizedtextheightlpc": {
      "command": "IEEEquantizedtextheightlpc",
      "snippet": "IEEEquantizedtextheightlpc",
      "option": "",
      "keyvals": [],
      "keyvalindex": -1
    },
    "IEEEquantizelength{}{}{}": {
      "command": "IEEEquantizelength{}{}{}",
      "snippet": "IEEEquantizelength{${1:mode}}{${2:unit}}{${3:length}}",
      "option": "",
      "keyvals": [],
      "keyvalindex": -1
    },
    "IEEEquantizetextheight[]{}": {
      "command": "IEEEquantizetextheight[]{}",
      "snippet": "IEEEquantizetextheight[${2:unit}]{${1:mode}}",
      "option": "",
      "keyvals": [],
      "keyvalindex": -1
    },
    "IEEEquantizetextheight{}": {
      "command": "IEEEquantizetextheight{}",
      "snippet": "IEEEquantizetextheight{${1:mode}}",
      "option": "",
      "keyvals": [],
      "keyvalindex": -1
    },
    "IEEEsetfootermargin[][]{}{}": {
      "command": "IEEEsetfootermargin[][]{}{}",
      "snippet": "IEEEsetfootermargin[${3:footer sample}][${4:text sample}]{${1:mode}}{${2:margin}}",
      "option": "",
      "keyvals": [],
      "keyvalindex": -1
    },
    "IEEEsetfootermargin[]{}{}": {
      "command": "IEEEsetfootermargin[]{}{}",
      "snippet": "IEEEsetfootermargin[${3:footer sample}]{${1:mode}}{${2:margin}}",
      "option": "",
      "keyvals": [],
      "keyvalindex": -1
    },
    "IEEEsetfootermargin{}{}": {
      "command": "IEEEsetfootermargin{}{}",
      "snippet": "IEEEsetfootermargin{${1:mode}}{${2:margin}}",
      "option": "",
      "keyvals": [],
      "keyvalindex": -1
    },
    "IEEEsetheadermargin[][]{}{}": {
      "command": "IEEEsetheadermargin[][]{}{}",
      "snippet": "IEEEsetheadermargin[${3:header sample}][${4:text sample}]{${1:mode}}{${2:margin}}",
      "option": "",
      "keyvals": [],
      "keyvalindex": -1
    },
    "IEEEsetheadermargin[]{}{}": {
      "command": "IEEEsetheadermargin[]{}{}",
      "snippet": "IEEEsetheadermargin[${3:header sample}]{${1:mode}}{${2:margin}}",
      "option": "",
      "keyvals": [],
      "keyvalindex": -1
    },
    "IEEEsetheadermargin{}{}": {
      "command": "IEEEsetheadermargin{}{}",
      "snippet": "IEEEsetheadermargin{${1:mode}}{${2:margin}}",
      "option": "",
      "keyvals": [],
      "keyvalindex": -1
    },
    "IEEEsetsidemargin{}{}": {
      "command": "IEEEsetsidemargin{}{}",
      "snippet": "IEEEsetsidemargin{${1:mode}}{${2:margin}}",
      "option": "",
      "keyvals": [],
      "keyvalindex": -1
    },
    "IEEEsettextheight[]{}{}": {
      "command": "IEEEsettextheight[]{}{}",
      "snippet": "IEEEsettextheight[${3:mode}]{${1:top margin}}{${2:bottom margin}}",
      "option": "",
      "keyvals": [],
      "keyvalindex": -1
    },
    "IEEEsettextheight{}{}": {
      "command": "IEEEsettextheight{}{}",
      "snippet": "IEEEsettextheight{${1:top margin}}{${2:bottom margin}}",
      "option": "",
      "keyvals": [],
      "keyvalindex": -1
    },
    "IEEEsettextwidth{}{}": {
      "command": "IEEEsettextwidth{}{}",
      "snippet": "IEEEsettextwidth{${1:inner margin}}{${2:outer margin}}",
      "option": "",
      "keyvals": [],
      "keyvalindex": -1
    },
    "IEEEsettopmargin[]{}{}": {
      "command": "IEEEsettopmargin[]{}{}",
      "snippet": "IEEEsettopmargin[${3:sample text}]{${1:mode}}{${2:margin}}",
      "option": "",
      "keyvals": [],
      "keyvalindex": -1
    },
    "IEEEsettopmargin{}{}": {
      "command": "IEEEsettopmargin{}{}",
      "snippet": "IEEEsettopmargin{${1:mode}}{${2:margin}}",
      "option": "",
      "keyvals": [],
      "keyvalindex": -1
    }
  },
  "envs": {
    "IEEEproof": {
      "name": "IEEEproof",
      "detail": "IEEEproof",
      "snippet": "",
      "option": "",
      "keyvals": [],
      "keyvalindex": -1
    },
    "IEEEproof[]": {
      "name": "IEEEproof",
      "detail": "IEEEproof[]",
      "snippet": "[${1:header%text}]",
      "option": "",
      "keyvals": [],
      "keyvalindex": -1
    },
    "enumerate[]": {
      "name": "enumerate",
      "detail": "enumerate[]",
      "snippet": "[${1:decl}]",
      "option": "",
      "keyvals": [],
      "keyvalindex": -1
    },
    "itemize[]": {
      "name": "itemize",
      "detail": "itemize[]",
      "snippet": "[${1:decl}]",
      "option": "",
      "keyvals": [],
      "keyvalindex": -1
    },
    "description[]": {
      "name": "description",
      "detail": "description[]",
      "snippet": "[${1:decl}]",
      "option": "",
      "keyvals": [],
      "keyvalindex": -1
    },
    "IEEEenumerate": {
      "name": "IEEEenumerate",
      "detail": "IEEEenumerate",
      "snippet": "",
      "option": "",
      "keyvals": [],
      "keyvalindex": -1
    },
    "IEEEenumerate[]": {
      "name": "IEEEenumerate",
      "detail": "IEEEenumerate[]",
      "snippet": "[${1:decl}]",
      "option": "",
      "keyvals": [],
      "keyvalindex": -1
    },
    "IEEEitemize": {
      "name": "IEEEitemize",
      "detail": "IEEEitemize",
      "snippet": "",
      "option": "",
      "keyvals": [],
      "keyvalindex": -1
    },
    "IEEEitemize[]": {
      "name": "IEEEitemize",
      "detail": "IEEEitemize[]",
      "snippet": "[${1:decl}]",
      "option": "",
      "keyvals": [],
      "keyvalindex": -1
    },
    "IEEEdescription": {
      "name": "IEEEdescription",
      "detail": "IEEEdescription",
      "snippet": "",
      "option": "",
      "keyvals": [],
      "keyvalindex": -1
    },
    "IEEEdescription[]": {
      "name": "IEEEdescription",
      "detail": "IEEEdescription[]",
      "snippet": "[${1:decl}]",
      "option": "",
      "keyvals": [],
      "keyvalindex": -1
    },
    "LaTeXenumerate": {
      "name": "LaTeXenumerate",
      "detail": "LaTeXenumerate",
      "snippet": "",
      "option": "",
      "keyvals": [],
      "keyvalindex": -1
    },
    "LaTeXitemize": {
      "name": "LaTeXitemize",
      "detail": "LaTeXitemize",
      "snippet": "",
      "option": "",
      "keyvals": [],
      "keyvalindex": -1
    },
    "LaTeXdescription": {
      "name": "LaTeXdescription",
      "detail": "LaTeXdescription",
      "snippet": "",
      "option": "",
      "keyvals": [],
      "keyvalindex": -1
    },
    "IEEEeqnarray{}": {
      "name": "IEEEeqnarray",
      "detail": "IEEEeqnarray{}",
      "snippet": "{${1:cols}}",
      "option": "",
      "keyvals": [],
      "keyvalindex": -1
    },
    "IEEEeqnarray[]{}": {
      "name": "IEEEeqnarray",
      "detail": "IEEEeqnarray[]{}",
      "snippet": "[${2:decl}]{${1:cols}}",
      "option": "",
      "keyvals": [],
      "keyvalindex": -1
    },
    "IEEEeqnarray*{}": {
      "name": "IEEEeqnarray*",
      "detail": "IEEEeqnarray*{}",
      "snippet": "{${1:cols}}",
      "option": "",
      "keyvals": [],
      "keyvalindex": -1
    },
    "IEEEeqnarray*[]{}": {
      "name": "IEEEeqnarray*",
      "detail": "IEEEeqnarray*[]{}",
      "snippet": "[${2:decl}]{${1:cols}}",
      "option": "",
      "keyvals": [],
      "keyvalindex": -1
    },
    "IEEEeqnarraybox{}": {
      "name": "IEEEeqnarraybox",
      "detail": "IEEEeqnarraybox{}",
      "snippet": "{${1:cols}}",
      "option": "",
      "keyvals": [],
      "keyvalindex": -1
    },
    "IEEEeqnarraybox[]{}": {
      "name": "IEEEeqnarraybox",
      "detail": "IEEEeqnarraybox[]{}",
      "snippet": "[${2:decl}]{${1:cols}}",
      "option": "",
      "keyvals": [],
      "keyvalindex": -1
    },
    "IEEEeqnarraybox[][]{}": {
      "name": "IEEEeqnarraybox",
      "detail": "IEEEeqnarraybox[][]{}",
      "snippet": "[${2:decl}][${3:pos}]{${1:cols}}",
      "option": "",
      "keyvals": [],
      "keyvalindex": -1
    },
    "IEEEeqnarraybox[][][]{}": {
      "name": "IEEEeqnarraybox",
      "detail": "IEEEeqnarraybox[][][]{}",
      "snippet": "[${2:decl}][${3:pos}][${4:width}]{${1:cols}}",
      "option": "",
      "keyvals": [],
      "keyvalindex": -1
    },
    "IEEEeqnarraybox*{}": {
      "name": "IEEEeqnarraybox*",
      "detail": "IEEEeqnarraybox*{}",
      "snippet": "{${1:cols}}",
      "option": "",
      "keyvals": [],
      "keyvalindex": -1
    },
    "IEEEeqnarraybox*[]{}": {
      "name": "IEEEeqnarraybox*",
      "detail": "IEEEeqnarraybox*[]{}",
      "snippet": "[${2:decl}]{${1:cols}}",
      "option": "",
      "keyvals": [],
      "keyvalindex": -1
    },
    "IEEEeqnarraybox*[][]{}": {
      "name": "IEEEeqnarraybox*",
      "detail": "IEEEeqnarraybox*[][]{}",
      "snippet": "[${2:decl}][${3:pos}]{${1:cols}}",
      "option": "",
      "keyvals": [],
      "keyvalindex": -1
    },
    "IEEEeqnarraybox*[][][]{}": {
      "name": "IEEEeqnarraybox*",
      "detail": "IEEEeqnarraybox*[][][]{}",
      "snippet": "[${2:decl}][${3:pos}][${4:width}]{${1:cols}}",
      "option": "",
      "keyvals": [],
      "keyvalindex": -1
    },
    "IEEEeqnarrayboxm{}": {
      "name": "IEEEeqnarrayboxm",
      "detail": "IEEEeqnarrayboxm{}",
      "snippet": "{${1:cols}}",
      "option": "",
      "keyvals": [],
      "keyvalindex": -1
    },
    "IEEEeqnarrayboxm[]{}": {
      "name": "IEEEeqnarrayboxm",
      "detail": "IEEEeqnarrayboxm[]{}",
      "snippet": "[${2:decl}]{${1:cols}}",
      "option": "",
      "keyvals": [],
      "keyvalindex": -1
    },
    "IEEEeqnarrayboxm[][]{}": {
      "name": "IEEEeqnarrayboxm",
      "detail": "IEEEeqnarrayboxm[][]{}",
      "snippet": "[${2:decl}][${3:pos}]{${1:cols}}",
      "option": "",
      "keyvals": [],
      "keyvalindex": -1
    },
    "IEEEeqnarrayboxm[][][]{}": {
      "name": "IEEEeqnarrayboxm",
      "detail": "IEEEeqnarrayboxm[][][]{}",
      "snippet": "[${2:decl}][${3:pos}][${4:width}]{${1:cols}}",
      "option": "",
      "keyvals": [],
      "keyvalindex": -1
    },
    "IEEEeqnarrayboxm*{}": {
      "name": "IEEEeqnarrayboxm*",
      "detail": "IEEEeqnarrayboxm*{}",
      "snippet": "{${1:cols}}",
      "option": "",
      "keyvals": [],
      "keyvalindex": -1
    },
    "IEEEeqnarrayboxm*[]{}": {
      "name": "IEEEeqnarrayboxm*",
      "detail": "IEEEeqnarrayboxm*[]{}",
      "snippet": "[${2:decl}]{${1:cols}}",
      "option": "",
      "keyvals": [],
      "keyvalindex": -1
    },
    "IEEEeqnarrayboxm*[][]{}": {
      "name": "IEEEeqnarrayboxm*",
      "detail": "IEEEeqnarrayboxm*[][]{}",
      "snippet": "[${2:decl}][${3:pos}]{${1:cols}}",
      "option": "",
      "keyvals": [],
      "keyvalindex": -1
    },
    "IEEEeqnarrayboxm*[][][]{}": {
      "name": "IEEEeqnarrayboxm*",
      "detail": "IEEEeqnarrayboxm*[][][]{}",
      "snippet": "[${2:decl}][${3:pos}][${4:width}]{${1:cols}}",
      "option": "",
      "keyvals": [],
      "keyvalindex": -1
    },
    "IEEEeqnarrayboxt{}": {
      "name": "IEEEeqnarrayboxt",
      "detail": "IEEEeqnarrayboxt{}",
      "snippet": "{${1:cols}}",
      "option": "",
      "keyvals": [],
      "keyvalindex": -1
    },
    "IEEEeqnarrayboxt[]{}": {
      "name": "IEEEeqnarrayboxt",
      "detail": "IEEEeqnarrayboxt[]{}",
      "snippet": "[${2:decl}]{${1:cols}}",
      "option": "",
      "keyvals": [],
      "keyvalindex": -1
    },
    "IEEEeqnarrayboxt[][]{}": {
      "name": "IEEEeqnarrayboxt",
      "detail": "IEEEeqnarrayboxt[][]{}",
      "snippet": "[${2:decl}][${3:pos}]{${1:cols}}",
      "option": "",
      "keyvals": [],
      "keyvalindex": -1
    },
    "IEEEeqnarrayboxt[][][]{}": {
      "name": "IEEEeqnarrayboxt",
      "detail": "IEEEeqnarrayboxt[][][]{}",
      "snippet": "[${2:decl}][${3:pos}][${4:width}]{${1:cols}}",
      "option": "",
      "keyvals": [],
      "keyvalindex": -1
    },
    "IEEEeqnarrayboxt*{}": {
      "name": "IEEEeqnarrayboxt*",
      "detail": "IEEEeqnarrayboxt*{}",
      "snippet": "{${1:cols}}",
      "option": "",
      "keyvals": [],
      "keyvalindex": -1
    },
    "IEEEeqnarrayboxt*[]{}": {
      "name": "IEEEeqnarrayboxt*",
      "detail": "IEEEeqnarrayboxt*[]{}",
      "snippet": "[${2:decl}]{${1:cols}}",
      "option": "",
      "keyvals": [],
      "keyvalindex": -1
    },
    "IEEEeqnarrayboxt*[][]{}": {
      "name": "IEEEeqnarrayboxt*",
      "detail": "IEEEeqnarrayboxt*[][]{}",
      "snippet": "[${2:decl}][${3:pos}]{${1:cols}}",
      "option": "",
      "keyvals": [],
      "keyvalindex": -1
    },
    "IEEEeqnarrayboxt*[][][]{}": {
      "name": "IEEEeqnarrayboxt*",
      "detail": "IEEEeqnarrayboxt*[][][]{}",
      "snippet": "[${2:decl}][${3:pos}][${4:width}]{${1:cols}}",
      "option": "",
      "keyvals": [],
      "keyvalindex": -1
    }
  },
  "options": [
    "redeflists"
  ]
}