{
  "includes": [
    "processkv"
  ],
  "cmds": {
    "colchunk{}": {
      "command": "colchunk{}",
      "snippet": "colchunk{${1:chunk%text}}",
      "option": "",
      "keyvals": [],
      "keyvalindex": -1
    },
    "colchunk[]{}": {
      "command": "colchunk[]{}",
      "snippet": "colchunk[${2:column}]{${1:chunk%text}}",
      "option": "",
      "keyvals": [],
      "keyvalindex": -1
    },
    "colplacechunks": {
      "command": "colplacechunks",
      "snippet": "colplacechunks",
      "option": "",
      "keyvals": [],
      "keyvalindex": -1
    }
  },
  "envs": {
    "parcolumns{}": {
      "name": "parcolumns",
      "detail": "parcolumns{}",
      "snippet": "{${1:number of cols}}",
      "option": "",
      "keyvals": [],
      "keyvalindex": -1
    },
    "parcolumns[]{}": {
      "name": "parcolumns",
      "detail": "parcolumns[]{}",
      "snippet": "[${2:options}]{${1:number of cols}}",
      "option": "",
      "keyvals": [
        "colwidths={",
        "distance=",
        "rulebetween",
        "nofirstindent",
        "sloppy",
        "sloppyspaces"
      ],
      "keyvalindex": 0
    }
  },
  "options": []
}